Workbook

Sheet 使用说明
A1: 审计风险评估热力图谱 · 使用说明
A3: 【模型】综合影响 = MAX(五维加权分, 一票否决系数×最高维度分)：任一维度打 4/5 分时，致命后果不被其他低分维度稀释。
A4: 风险领域 12 个、4 大类（战略与治理/财务/运营/合规与安全），对齐《企业内部控制应用指引》与《中央企业全面风险管理指引》。
A5: 五维权重按“所属领域”自动取用分领域权重矩阵（参数配置页 A24 起），未列出的领域用“全领域默认”行。
A6: 固有风险 = 可能性(1-5) × 综合影响；剩余风险 = 固有 × (1−折减系数)。
A7: 折减系数由该风险“关键控制点”的最低分查映射表确定（短板效应）；未标记关键控制时退回全部控制点取最低；无控制点则不折减。
A8: 控制挽回率 = (固有−剩余)/固有，衡量控制环境化解风险的比例，见登记册 V 列与汇总页领域表。
A9: 打分原则：各维度只评估其专属后果（如经济损失维度不重复计入舞弊造成的损失），避免维度间重复计分。
A10: 等级五档：极高≥20 / 高≥12 / 中≥6 / 低≥3 / 极低<3（可在参数配置页调整）。
A12: 【日常操作】1. 在「风险登记册」黄色列维护风险条目与六项打分（下拉限选 1-5、领域、期间）。
A13: 2. 在「控制措施表」为每条风险挂控制点、打有效性分并标记是否关键控制，注意选对评估期间。
A14: 3. 打开「热力图」页切换评估期间查看固有/剩余矩阵；「汇总与优先级」页看排序清单与领域挽回率。
... A22: 【约定】黄色单元格＝手工录入；灰色单元格＝公式自动计算，请勿覆盖。

Sheet 参数配置
A1: 参数配置 —— 修改后全簿公式自动联动 | I1: 评估期间清单
A2: 五维影响权重 | I2: 全部
A3: 经济损失权重 | B3: 0.3 | D3: 控制分 | E3: 折减系数 | I3: 2025H2 | J3: 登记册/控制措施表/热力图的下拉自动引用本清单；新增评估期间在下方空行填写即可
A4: 合规法律权重 | B4: 0.25 | D4: 1 | E4: 0 | I4: 2026H1
A5: 运营中断权重 | B5: 0.15 | D5: 2 | E5: 0.15
A6: 声誉舆情权重 | B6: 0.15 | D6: 3 | E6: 0.4
A7: 舞弊风险权重 | B7: 0.15 | D7: 4 | E7: 0.55
A8: 权重合计（必须=1） | B8: =SUM(B3:B7) | D8: 5 | E8: 0.7
A9: 注：五个权重之和不为 1 时，合计单元格变红，导出脚本将拒绝执行。 | D9: 短板效应：剩余风险按单条风险“关键控制点最低分”取折减系数（无关键标记则按全部控制点最低分）
D10: 参考折减系数 | E10: 0.4
A11: 剩余风险等级阈值（≥） | D11: 仅用于热力图页剩余矩阵的着色基准
A12: 极高风险 | B12: 20
A13: 高风险 | B13: 12 | D13: 一票否决系数 | E13: 0.75
A14: 中风险 | B14: 6 | D14: 综合影响 = MAX(加权分, 该系数×最高维度分)：任一维度打高分时致命后果不被其他维度稀释
A15: 低风险 | B15: 3
A17: 颜色图例
A18: 极高
A19: 高
A20: 中
A21: 低
A22: 极低
A24: 分领域影响权重矩阵（各行列合计须=1；登记册领域未列出时自动使用“全领域默认”行）
A25: 领域＼维度 | B25: 经济损失 | C25: 合规法律 | D25: 运营中断 | E25: 声誉舆情 | F25: 舞弊风险 | G25: 行合计
A26: 全领域默认 | B26: 0.3 | C26: 0.25 | D26: 0.15 | E26: 0.15 | F26: 0.15 | G26: =SUM(B26:F26)
A27: 战略与投资 | B27: 0.3 | C27: 0.15 | D27: 0.25 | E27: 0.25 | F27: 0.05 | G27: =SUM(B27:F27)
A28: 治理与决策 | B28: 0.25 | C28: 0.25 | D28: 0.15 | E28: 0.25 | F28: 0.1 | G28: =SUM(B28:F28)
A29: 资金活动 | B29: 0.4 | C29: 0.25 | D29: 0.1 | E29: 0.15 | F29: 0.1 | G29: =SUM(B29:F29)
A30: 财务报告与税务 | B30: 0.35 | C30: 0.3 | D30: 0.1 | E30: 0.2 | F30: 0.05 | G30: =SUM(B30:F30)
A31: 资产管理 | B31: 0.4 | C31: 0.1 | D31: 0.2 | E31: 0.15 | F31: 0.15 | G31: =SUM(B31:F31)
A32: 采购与外包 | B32: 0.25 | C32: 0.25 | D32: 0.1 | E32: 0.15 | F32: 0.25 | G32: =SUM(B32:F32)
A33: 合同管理 | B33: 0.25 | C33: 0.3 | D33: 0.15 | E33: 0.2 | F33: 0.1 | G33: =SUM(B33:F33)
A34: 工程项目 | B34: 0.35 | C34: 0.15 | D34: 0.2 | E34: 0.2 | F34: 0.1 | G34: =SUM(B34:F34)
A35: 人力资源 | B35: 0.2 | C35: 0.2 | D35: 0.25 | E35: 0.2 | F35: 0.15 | G35: =SUM(B35:F35)
A36: 信息系统 | B36: 0.15 | C36: 0.15 | D36: 0.35 | E36: 0.2 | F36: 0.15 | G36: =SUM(B36:F36)
A37: 合规与法律 | B37: 0.15 | C37: 0.45 | D37: 0.1 | E37: 0.25 | F37: 0.05 | G37: =SUM(B37:F37)
A38: 安全环保 | B38: 0.15 | C38: 0.3 | D38: 0.3 | E38: 0.25 | F38: 0 | G38: =SUM(B38:F38)

Sheet 风险登记册
A1: 风险登记册（黄色列录入，灰色列自动计算，请勿改写公式）
A3: 风险编号 | B3: 风险名称 | C3: 所属领域 | D3: 风险描述 | E3: 责任部门 | F3: 评估期间 | G3: 发生可能性 (1-5) | H3: 经济损失 (1-5) | I3: 合规法律 (1-5) | J3: 运营中断 (1-5) | K3: 声誉舆情 (1-5) | L3: 舞弊风险 (1-5) | M3: 综合影响 | N3: 固有风险 | O3: 最弱控制分 | P3: 折减系数 | Q3: 剩余风险 | R3: 剩余等级 | S3: 影响档 (辅助) | T3: 固有档 (辅助) | U3: 建议审计频次 | V3: 控制挽回率 | W3: 打分依据
A4: R001 | B4: 费用报销合规风险 | C4: 资金活动 | D4: 大额异常费用报销审核不到位，存在虚假报销套取资金可能 | E4: 财务部 | F4: 2025H2 | G4: 4 | H4: 4 | I4: 4 | J4: 2 | K4: 3 | L4: 5 | M4: =IF($A4="","",ROUND(MAX(SUMPRODUCT(H4:L4,IFERROR(VLOOKUP($C4,参数配置!$A$26:$F$38,{2,3,4,5,6},FALSE),VLOOKUP(参数配置!$A$26,参数配置!$A$26:$F$38,{2,3,4,5,6},FALSE))),参数配置!$E$13*MAX(H4:L4)),2)) | N4: =IF($A4="","",ROUND(G4*M4,2)) | O4: =IF($A4="","",IF(COUNTIFS(控制措施表!$B:$B,$A4,控制措施表!$C:$C,$F4,控制措施表!$F:$F,"是")=0,IF(COUNTIFS(控制措施表!$B:$B,$A4,控制措施表!$C:$C,$F4)=0,"",MINIFS(控制措施表!$E:$E,控制措施表!$B:$B,$A4,控制措施表!$C:$C,$F4)),MINIFS(控制措施表!$E:$E,控制措施表!$B:$B,$A4,控制措施表!$C:$C,$F4,控制措施表!$F:$F,"是"))) | P4: =IF($A4="","",IF(N4="",0,VLOOKUP(N4,参数配置!$D$4:$E$8,2,FALSE))) | Q4: =IF($A4="","",ROUND(O4*(1-P4),2)) | R4: =IF($A4="","",IF(Q4>=参数配置!$B$12,"极高",IF(Q4>=参数配置!$B$13,"高",IF(Q4>=参数配置!$B$14,"中",IF(Q4>=参数配置!$B$15,"低","极低"))))) | S4: =IF($A4="","",ROUND(M4,0)) | T4: =IF($A4="","",ROUND(N4,0)) | U4: =IF($A4="","",IF(R4="极高","每年必审",IF(R4="高","每年审计",IF(R4="中","两年一轮","按需抽查")))) | V4: =IF($A4="","",IF(N4=0,"",(N4-Q4)/N4)) | W4: 2025 年内审抽查发现 3 笔超标准报销；预算系统 2025Q4 上线刚性拦截
A5: R001 | B5: 费用报销合规风险 | C5: 资金活动 | D5: 大额异常费用报销审核不到位，存在虚假报销套取资金可能 | E5: 财务部 | F5: 2026H1 | G5: 3 | H5: 4 | I5: 4 | J5: 2 | K5: 3 | L5: 4 | M5: =IF($A5="","",ROUND(MAX(SUMPRODUCT(H5:L5,IFERROR(VLOOKUP($C5,参数配置!$A$26:$F$38,{2,3,4,5,6},FALSE),VLOOKUP(参数配置!$A$26,参数配置!$A$26:$F$38,{2,3,4,5,6},FALSE))),参数配置!$E$13*MAX(H5:L5)),2)) | N5: =IF($A5="","",ROUND(G5*M5,2)) | O5: =IF($A5="","",IF(COUNTIFS(控制措施表!$B:$B,$A5,控制措施表!$C:$C,$F5,控制措施表!$F:$F,"是")=0,IF(COUNTIFS(控制措施表!$B:$B,$A5,控制措施表!$C:$C,$F5)=0,"",MINIFS(控制措施表!$E:$E,控制措施表!$B:$B,$A5,控制措施表!$C:$C,$F5)),MINIFS(控制措施表!$E:$E,控制措施表!$B:$B,$A5,控制措施表!$C:$C,$F5,控制措施表!$F:$F,"是"))) | P5: =IF($A5="","",IF(N5="",0,VLOOKUP(N5,参数配置!$D$4:$E$8,2,FALSE))) | Q5: =IF($A5="","",ROUND(O5*(1-P5),2)) | R5: =IF($A5="","",IF(Q5>=参数配置!$B$12,"极高",IF(Q5>=参数配置!$B$13,"高",IF(Q5>=参数配置!$B$14,"中",IF(Q5>=参数配置!$B$15,"低","极低"))))) | S5: =IF($A5="","",ROUND(M5,0)) | T5: =IF($A5="","",ROUND(N5,0)) | U5: =IF($A5="","",IF(R5="极高","每年必审",IF(R5="高","每年审计",IF(R5="中","两年一轮","按需抽查")))) | V5: =IF($A5="","",IF(N5=0,"",(N5-Q5)/N5)) | W5: 2025 年内审抽查发现 3 笔超标准报销；预算系统 2025Q4 上线刚性拦截
A6: R002 | B6: 收入确认完整性 | C6: 财务报告与税务 | D6: 收入截止性错误或提前确认，导致财报失真 | E6: 财务部 | F6: 2025H2 | G6: 3 | H6: 5 | I6: 4 | J6: 3 | K6: 4 | L6: 2 | M6: =IF($A6="","",ROUND(MAX(SUMPRODUCT(H6:L6,IFERROR(VLOOKUP($C6,参数配置!$A$26:$F$38,{2,3,4,5,6},FALSE),VLOOKUP(参数配置!$A$26,参数配置!$A$26:$F$38,{2,3,4,5,6},FALSE))),参数配置!$E$13*MAX(H6:L6)),2)) | N6: =IF($A6="","",ROUND(G6*M6,2)) | O6: =IF($A6="","",IF(COUNTIFS(控制措施表!$B:$B,$A6,控制措施表!$C:$C,$F6,控制措施表!$F:$F,"是")=0,IF(COUNTIFS(控制措施表!$B:$B,$A6,控制措施表!$C:$C,$F6)=0,"",MINIFS(控制措施表!$E:$E,控制措施表!$B:$B,$A6,控制措施表!$C:$C,$F6)),MINIFS(控制措施表!$E:$E,控制措施表!$B:$B,$A6,控制措施表!$C:$C,$F6,控制措施表!$F:$F,"是"))) | P6: =IF($A6="","",IF(N6="",0,VLOOKUP(N6,参数配置!$D$4:$E$8,2,FALSE))) | Q6: =IF($A6="","",ROUND(O6*(1-P6),2)) | R6: =IF($A6="","",IF(Q6>=参数配置!$B$12,"极高",IF(Q6>=参数配置!$B$13,"高",IF(Q6>=参数配置!$B$14,"中",IF(Q6>=参数配置!$B$15,"低","极低"))))) | S6: =IF($A6="","",ROUND(M6,0)) | T6: =IF($A6="","",ROUND(N6,0)) | U6: =IF($A6="","",IF(R6="极高","每年必审",IF(R6="高","每年审计",IF(R6="中","两年一轮","按需抽查")))) | V6: =IF($A6="","",IF(N6=0,"",(N6-Q6)/N6)) | W6: 上年度审计调整收入截止事项 2 项，涉及金额 120 万元
A7: R002 | B7: 收入确认完整性 | C7: 财务报告与税务 | D7: 收入截止性错误或提前确认，导致财报失真 | E7: 财务部 | F7: 2026H1 | G7: 2 | H7: 5 | I7: 4 | J7: 3 | K7: 4 | L7: 2 | M7: =IF($A7="","",ROUND(MAX(SUMPRODUCT(H7:L7,IFERROR(VLOOKUP($C7,参数配置!$A$26:$F$38,{2,3,4,5,6},FALSE),VLOOKUP(参数配置!$A$26,参数配置!$A$26:$F$38,{2,3,4,5,6},FALSE))),参数配置!$E$13*MAX(H7:L7)),2)) | N7: =IF($A7="","",ROUND(G7*M7,2)) | O7: =IF($A7="","",IF(COUNTIFS(控制措施表!$B:$B,$A7,控制措施表!$C:$C,$F7,控制措施表!$F:$F,"是")=0,IF(COUNTIFS(控制措施表!$B:$B,$A7,控制措施表!$C:$C,$F7)=0,"",MINIFS(控制措施表!$E:$E,控制措施表!$B:$B,$A7,控制措施表!$C:$C,$F7)),MINIFS(控制措施表!$E:$E,控制措施表!$B:$B,$A7,控制措施表!$C:$C,$F7,控制措施表!$F:$F,"是"))) | P7: =IF($A7="","",IF(N7="",0,VLOOKUP(N7,参数配置!$D$4:$E$8,2,FALSE))) | Q7: =IF($A7="","",ROUND(O7*(1-P7),2)) | R7: =IF($A7="","",IF(Q7>=参数配置!$B$12,"极高",IF(Q7>=参数配置!$B$13,"高",IF(Q7>=参数配置!$B$14,"中",IF(Q7>=参数配置!$B$15,"低","极低"))))) | S7: =IF($A7="","",ROUND(M7,0)) | T7: =IF($A7="","",ROUND(N7,0)) | U7: =IF($A7="","",IF(R7="极高","每年必审",IF(R7="高","每年审计",IF(R7="中","两年一轮","按需抽查")))) | V7: =IF($A7="","",IF(N7=0,"",(N7-Q7)/N7)) | W7: 上年度审计调整收入截止事项 2 项，涉及金额 120 万元
A8: R003 | B8: 资金支付越权审批 | C8: 资金活动 | D8: 超权限支付未履行集体决策程序，资金安全存在隐患 | E8: 财务部 | F8: 2025H2 | G8: 3 | H8: 5 | I8: 5 | J8: 3 | K8: 4 | L8: 4 | M8: =IF($A8="","",ROUND(MAX(SUMPRODUCT(H8:L8,IFERROR(VLOOKUP($C8,参数配置!$A$26:$F$38,{2,3,4,5,6},FALSE),VLOOKUP(参数配置!$A$26,参数配置!$A$26:$F$38,{2,3,4,5,6},FALSE))),参数配置!$E$13*MAX(H8:L8)),2)) | N8: =IF($A8="","",ROUND(G8*M8,2)) | O8: =IF($A8="","",IF(COUNTIFS(控制措施表!$B:$B,$A8,控制措施表!$C:$C,$F8,控制措施表!$F:$F,"是")=0,IF(COUNTIFS(控制措施表!$B:$B,$A8,控制措施表!$C:$C,$F8)=0,"",MINIFS(控制措施表!$E:$E,控制措施表!$B:$B,$A8,控制措施表!$C:$C,$F8)),MINIFS(控制措施表!$E:$E,控制措施表!$B:$B,$A8,控制措施表!$C:$C,$F8,控制措施表!$F:$F,"是"))) | P8: =IF($A8="","",IF(N8="",0,VLOOKUP(N8,参数配置!$D$4:$E$8,2,FALSE))) | Q8: =IF($A8="","",ROUND(O8*(1-P8),2)) | R8: =IF($A8="","",IF(Q8>=参数配置!$B$12,"极高",IF(Q8>=参数配置!$B$13,"高",IF(Q8>=参数配置!$B$14,"中",IF(Q8>=参数配置!$B$15,"低","极低"))))) | S8: =IF($A8="","",ROUND(M8,0)) | T8: =IF($A8="","",ROUND(N8,0)) | U8: =IF($A8="","",IF(R8="极高","每年必审",IF(R8="高","每年审计",IF(R8="中","两年一轮","按需抽查")))) | V8: =IF($A8="","",IF(N8=0,"",(N8-Q8)/N8)) | W8: 资金制度修订后未再发现越权支付；网银复核日志抽查正常
A9: R003 | B9: 资金支付越权审批 | C9: 资金活动 | D9: 超权限支付未履行集体决策程序，资金安全存在隐患 | E9: 财务部 | F9: 2026H1 | G9: 2 | H9: 5 | I9: 5 | J9: 3 | K9: 4 | L9: 4 | M9: =IF($A9="","",ROUND(MAX(SUMPRODUCT(H9:L9,IFERROR(VLOOKUP($C9,参数配置!$A$26:$F$38,{2,3,4,5,6},FALSE),VLOOKUP(参数配置!$A$26,参数配置!$A$26:$F$38,{2,3,4,5,6},FALSE))),参数配置!$E$13*MAX(H9:L9)),2)) | N9: =IF($A9="","",ROUND(G9*M9,2)) | O9: =IF($A9="","",IF(COUNTIFS(控制措施表!$B:$B,$A9,控制措施表!$C:$C,$F9,控制措施表!$F:$F,"是")=0,IF(COUNTIFS(控制措施表!$B:$B,$A9,控制措施表!$C:$C,$F9)=0,"",MINIFS(控制措施表!$E:$E,控制措施表!$B:$B,$A9,控制措施表!$C:$C,$F9)),MINIFS(控制措施表!$E:$E,控制措施表!$B:$B,$A9,控制措施表!$C:$C,$F9,控制措施表!$F:$F,"是"))) | P9: =IF($A9="","",IF(N9="",0,VLOOKUP(N9,参数配置!$D$4:$E$8,2,FALSE))) | Q9: =IF($A9="","",ROUND(O9*(1-P9),2)) | R9: =IF($A9="","",IF(Q9>=参数配置!$B$12,"极高",IF(Q9>=参数配置!$B$13,"高",IF(Q9>=参数配置!$B$14,"中",IF(Q9>=参数配置!$B$15,"低","极低"))))) | S9: =IF($A9="","",ROUND(M9,0)) | T9: =IF($A9="","",ROUND(N9,0)) | U9: =IF($A9="","",IF(R9="极高","每年必审",IF(R9="高","每年审计",IF(R9="中","两年一轮","按需抽查")))) | V9: =IF($A9="","",IF(N9=0,"",(N9-Q9)/N9)) | W9: 资金制度修订后未再发现越权支付；网银复核日志抽查正常
A10: R004 | B10: 供应商准入与围标串标 | C10: 采购与外包 | D10: 准入把关不严，关联供应商围标串标，采购价格虚高 | E10: 采购部 | F10: 2025H2 | G10: 4 | H10: 4 | I10: 4 | J10: 3 | K10: 4 | L10: 5 | M10: =IF($A10="","",ROUND(MAX(SUMPRODUCT(H10:L10,IFERROR(VLOOKUP($C10,参数配置!$A$26:$F$38,{2,3,4,5,6},FALSE),VLOOKUP(参数配置!$A$26,参数配置!$A$26:$F$38,{2,3,4,5,6},FALSE))),参数配置!$E$13*MAX(H10:L10)),2)) | N10: =IF($A10="","",ROUND(G10*M10,2)) | O10: =IF($A10="","",IF(COUNTIFS(控制措施表!$B:$B,$A10,控制措施表!$C:$C,$F10,控制措施表!$F:$F,"是")=0,IF(COUNTIFS(控制措施表!$B:$B,$A10,控制措施表!$C:$C,$F10)=0,"",MINIFS(控制措施表!$E:$E,控制措施表!$B:$B,$A10,控制措施表!$C:$C,$F10)),MINIFS(控制措施表!$E:$E,控制措施表!$B:$B,$A10,控制措施表!$C:$C,$F10,控制措施表!$F:$F,"是"))) | P10: =IF($A10="","",IF(N10="",0,VLOOKUP(N10,参数配置!$D$4:$E$8,2,FALSE))) | Q10: =IF($A10="","",ROUND(O10*(1-P10),2)) | R10: =IF($A10="","",IF(Q10>=参数配置!$B$12,"极高",IF(Q10>=参数配置!$B$13,"高",IF(Q10>=参数配置!$B$14,"中",IF(Q10>=参数配置!$B$15,"低","极低"))))) | S10: =IF($A10="","",ROUND(M10,0)) | T10: =IF($A10="","",ROUND(N10,0)) | U10: =IF($A10="","",IF(R10="极高","每年必审",IF(R10="高","每年审计",IF(R10="中","两年一轮","按需抽查")))) | V10: =IF($A10="","",IF(N10=0,"",(N10-Q10)/N10)) | W10: 近两年招标投诉 2 起；关联供应商筛查发现 1 家未申报关联关系
A11: R004 | B11: 供应商准入与围标串标 | C11: 采购与外包 | D11: 准入把关不严，关联供应商围标串标，采购价格虚高 | E11: 采购部 | F11: 2026H1 | G11: 4 | H11: 4 | I11: 4 | J11: 3 | K11: 3 | L11: 5 | M11: =IF($A11="","",ROUND(MAX(SUMPRODUCT(H11:L11,IFERROR(VLOOKUP($C11,参数配置!$A$26:$F$38,{2,3,4,5,6},FALSE),VLOOKUP(参数配置!$A$26,参数配置!$A$26:$F$38,{2,3,4,5,6},FALSE))),参数配置!$E$13*MAX(H11:L11)),2)) | N11: =IF($A11="","",ROUND(G11*M11,2)) | O11: =IF($A11="","",IF(COUNTIFS(控制措施表!$B:$B,$A11,控制措施表!$C:$C,$F11,控制措施表!$F:$F,"是")=0,IF(COUNTIFS(控制措施表!$B:$B,$A11,控制措施表!$C:$C,$F11)=0,"",MINIFS(控制措施表!$E:$E,控制措施表!$B:$B,$A11,控制措施表!$C:$C,$F11)),MINIFS(控制措施表!$E:$E,控制措施表!$B:$B,$A11,控制措施表!$C:$C,$F11,控制措施表!$F:$F,"是"))) | P11: =IF($A11="","",IF(N11="",0,VLOOKUP(N11,参数配置!$D$4:$E$8,2,FALSE))) | Q11: =IF($A11="","",ROUND(O11*(1-P11),2)) | R11: =IF($A11="","",IF(Q11>=参数配置!$B$12,"极高",IF(Q11>=参数配置!$B$13,"高",IF(Q11>=参数配置!$B$14,"中",IF(Q11>=参数配置!$B$15,"低","极低"))))) | S11: =IF($A11="","",ROUND(M11,0)) | T11: =IF($A11="","",ROUND(N11,0)) | U11: =IF($A11="","",IF(R11="极高","每年必审",IF(R11="高","每年审计",IF(R11="中","两年一轮","按需抽查")))) | V11: =IF($A11="","",IF(N11=0,"",(N11-Q11)/N11)) | W11: 近两年招标投诉 2 起；关联供应商筛查发现 1 家未申报关联关系
A12: R005 | B12: 合同法律审查缺位 | C12: 合同管理 | D12: 合同条款未经法务审查即签署，履约纠纷败诉风险 | E12: 采购部 | F12: 2025H2 | G12: 3 | H12: 4 | I12: 5 | J12: 4 | K12: 4 | L12: 3 | M12: =IF($A12="","",ROUND(MAX(SUMPRODUCT(H12:L12,IFERROR(VLOOKUP($C12,参数配置!$A$26:$F$38,{2,3,4,5,6},FALSE),VLOOKUP(参数配置!$A$26,参数配置!$A$26:$F$38,{2,3,4,5,6},FALSE))),参数配置!$E$13*MAX(H12:L12)),2)) | N12: =IF($A12="","",ROUND(G12*M12,2)) | O12: =IF($A12="","",IF(COUNTIFS(控制措施表!$B:$B,$A12,控制措施表!$C:$C,$F12,控制措施表!$F:$F,"是")=0,IF(COUNTIFS(控制措施表!$B:$B,$A12,控制措施表!$C:$C,$F12)=0,"",MINIFS(控制措施表!$E:$E,控制措施表!$B:$B,$A12,控制措施表!$C:$C,$F12)),MINIFS(控制措施表!$E:$E,控制措施表!$B:$B,$A12,控制措施表!$C:$C,$F12,控制措施表!$F:$F,"是"))) | P12: =IF($A12="","",IF(N12="",0,VLOOKUP(N12,参数配置!$D$4:$E$8,2,FALSE))) | Q12: =IF($A12="","",ROUND(O12*(1-P12),2)) | R12: =IF($A12="","",IF(Q12>=参数配置!$B$12,"极高",IF(Q12>=参数配置!$B$13,"高",IF(Q12>=参数配置!$B$14,"中",IF(Q12>=参数配置!$B$15,"低","极低"))))) | S12: =IF($A12="","",ROUND(M12,0)) | T12: =IF($A12="","",ROUND(N12,0)) | U12: =IF($A12="","",IF(R12="极高","每年必审",IF(R12="高","每年审计",IF(R12="中","两年一轮","按需抽查")))) | V12: =IF($A12="","",IF(N12=0,"",(N12-Q12)/N12)) | W12: 法律纠纷台账 2 起未决诉讼均涉合同条款缺陷
A13: R005 | B13: 合同法律审查缺位 | C13: 合同管理 | D13: 合同条款未经法务审查即签署，履约纠纷败诉风险 | E13: 采购部 | F13: 2026H1 | G13: 3 | H13: 4 | I13: 5 | J13: 4 | K13: 3 | L13: 3 | M13: =IF($A13="","",ROUND(MAX(SUMPRODUCT(H13:L13,IFERROR(VLOOKUP($C13,参数配置!$A$26:$F$38,{2,3,4,5,6},FALSE),VLOOKUP(参数配置!$A$26,参数配置!$A$26:$F$38,{2,3,4,5,6},FALSE))),参数配置!$E$13*MAX(H13:L13)),2)) | N13: =IF($A13="","",ROUND(G13*M13,2)) | O13: =IF($A13="","",IF(COUNTIFS(控制措施表!$B:$B,$A13,控制措施表!$C:$C,$F13,控制措施表!$F:$F,"是")=0,IF(COUNTIFS(控制措施表!$B:$B,$A13,控制措施表!$C:$C,$F13)=0,"",MINIFS(控制措施表!$E:$E,控制措施表!$B:$B,$A13,控制措施表!$C:$C,$F13)),MINIFS(控制措施表!$E:$E,控制措施表!$B:$B,$A13,控制措施表!$C:$C,$F13,控制措施表!$F:$F,"是"))) | P13: =IF($A13="","",IF(N13="",0,VLOOKUP(N13,参数配置!$D$4:$E$8,2,FALSE))) | Q13: =IF($A13="","",ROUND(O13*(1-P13),2)) | R13: =IF($A13="","",IF(Q13>=参数配置!$B$12,"极高",IF(Q13>=参数配置!$B$13,"高",IF(Q13>=参数配置!$B$14,"中",IF(Q13>=参数配置!$B$15,"低","极低"))))) | S13: =IF($A13="","",ROUND(M13,0)) | T13: =IF($A13="","",ROUND(N13,0)) | U13: =IF($A13="","",IF(R13="极高","每年必审",IF(R13="高","每年审计",IF(R13="中","两年一轮","按需抽查")))) | V13: =IF($A13="","",IF(N13=0,"",(N13-Q13)/N13)) | W13: 法律纠纷台账 2 起未决诉讼均涉合同条款缺陷
A14: R006 | B14: 到货验收流于形式 | C14: 采购与外包 | D14: 验收环节走过场，以次充好、数量短缺未被发现的可能 | E14: 采购部 | F14: 2025H2 | G14: 3 | H14: 4 | I14: 3 | J14: 4 | K14: 2 | L14: 4 | M14: =IF($A14="","",ROUND(MAX(SUMPRODUCT(H14:L14,IFERROR(VLOOKUP($C14,参数配置!$A$26:$F$38,{2,3,4,5,6},FALSE),VLOOKUP(参数配置!$A$26,参数配置!$A$26:$F$38,{2,3,4,5,6},FALSE))),参数配置!$E$13*MAX(H14:L14)),2)) | N14: =IF($A14="","",ROUND(G14*M14,2)) | O14: =IF($A14="","",IF(COUNTIFS(控制措施表!$B:$B,$A14,控制措施表!$C:$C,$F14,控制措施表!$F:$F,"是")=0,IF(COUNTIFS(控制措施表!$B:$B,$A14,控制措施表!$C:$C,$F14)=0,"",MINIFS(控制措施表!$E:$E,控制措施表!$B:$B,$A14,控制措施表!$C:$C,$F14)),MINIFS(控制措施表!$E:$E,控制措施表!$B:$B,$A14,控制措施表!$C:$C,$F14,控制措施表!$F:$F,"是"))) | P14: =IF($A14="","",IF(N14="",0,VLOOKUP(N14,参数配置!$D$4:$E$8,2,FALSE))) | Q14: =IF($A14="","",ROUND(O14*(1-P14),2)) | R14: =IF($A14="","",IF(Q14>=参数配置!$B$12,"极高",IF(Q14>=参数配置!$B$13,"高",IF(Q14>=参数配置!$B$14,"中",IF(Q14>=参数配置!$B$15,"低","极低"))))) | S14: =IF($A14="","",ROUND(M14,0)) | T14: =IF($A14="","",ROUND(N14,0)) | U14: =IF($A14="","",IF(R14="极高","每年必审",IF(R14="高","每年审计",IF(R14="中","两年一轮","按需抽查")))) | V14: =IF($A14="","",IF(N14=0,"",(N14-Q14)/N14)) | W14: 仓库验收单抽查 20% 缺少影像附件
A15: R006 | B15: 到货验收流于形式 | C15: 采购与外包 | D15: 验收环节走过场，以次充好、数量短缺未被发现的可能 | E15: 采购部 | F15: 2026H1 | G15: 3 | H15: 4 | I15: 3 | J15: 4 | K15: 2 | L15: 3 | M15: =IF($A15="","",ROUND(MAX(SUMPRODUCT(H15:L15,IFERROR(VLOOKUP($C15,参数配置!$A$26:$F$38,{2,3,4,5,6},FALSE),VLOOKUP(参数配置!$A$26,参数配置!$A$26:$F$38,{2,3,4,5,6},FALSE))),参数配置!$E$13*MAX(H15:L15)),2)) | N15: =IF($A15="","",ROUND(G15*M15,2)) | O15: =IF($A15="","",IF(COUNTIFS(控制措施表!$B:$B,$A15,控制措施表!$C:$C,$F15,控制措施表!$F:$F,"是")=0,IF(COUNTIFS(控制措施表!$B:$B,$A15,控制措施表!$C:$C,$F15)=0,"",MINIFS(控制措施表!$E:$E,控制措施表!$B:$B,$A15,控制措施表!$C:$C,$F15)),MINIFS(控制措施表!$E:$E,控制措施表!$B:$B,$A15,控制措施表!$C:$C,$F15,控制措施表!$F:$F,"是"))) | P15: =IF($A15="","",IF(N15="",0,VLOOKUP(N15,参数配置!$D$4:$E$8,2,FALSE))) | Q15: =IF($A15="","",ROUND(O15*(1-P15),2)) | R15: =IF($A15="","",IF(Q15>=参数配置!$B$12,"极高",IF(Q15>=参数配置!$B$13,"高",IF(Q15>=参数配置!$B$14,"中",IF(Q15>=参数配置!$B$15,"低","极低"))))) | S15: =IF($A15="","",ROUND(M15,0)) | T15: =IF($A15="","",ROUND(N15,0)) | U15: =IF($A15="","",IF(R15="极高","每年必审",IF(R15="高","每年审计",IF(R15="中","两年一轮","按需抽查")))) | V15: =IF($A15="","",IF(N15=0,"",(N15-Q15)/N15)) | W15: 仓库验收单抽查 20% 缺少影像附件
... A51: R024 | B51: 银行账户与票据管理 | C51: 资金活动 | D51: 账户开立失控、票据审核不严，存在欺诈损失风险 | E51: 财务部 | F51: 2026H1 | G51: 3 | H51: 4 | I51: 3 | J51: 3 | K51: 2 | L51: 4 | M51: =IF($A51="","",ROUND(MAX(SUMPRODUCT(H51:L51,IFERROR(VLOOKUP($C51,参数配置!$A$26:$F$38,{2,3,4,5,6},FALSE),VLOOKUP(参数配置!$A$26,参数配置!$A$26:$F$38,{2,3,4,5,6},FALSE))),参数配置!$E$13*MAX(H51:L51)),2)) | N51: =IF($A51="","",ROUND(G51*M51,2)) | O51: =IF($A51="","",IF(COUNTIFS(控制措施表!$B:$B,$A51,控制措施表!$C:$C,$F51,控制措施表!$F:$F,"是")=0,IF(COUNTIFS(控制措施表!$B:$B,$A51,控制措施表!$C:$C,$F51)=0,"",MINIFS(控制措施表!$E:$E,控制措施表!$B:$B,$A51,控制措施表!$C:$C,$F51)),MINIFS(控制措施表!$E:$E,控制措施表!$B:$B,$A51,控制措施表!$C:$C,$F51,控制措施表!$F:$F,"是"))) | P51: =IF($A51="","",IF(N51="",0,VLOOKUP(N51,参数配置!$D$4:$E$8,2,FALSE))) | Q51: =IF($A51="","",ROUND(O51*(1-P51),2)) | R51: =IF($A51="","",IF(Q51>=参数配置!$B$12,"极高",IF(Q51>=参数配置!$B$13,"高",IF(Q51>=参数配置!$B$14,"中",IF(Q51>=参数配置!$B$15,"低","极低"))))) | S51: =IF($A51="","",ROUND(M51,0)) | T51: =IF($A51="","",ROUND(N51,0)) | U51: =IF($A51="","",IF(R51="极高","每年必审",IF(R51="高","每年审计",IF(R51="中","两年一轮","按需抽查")))) | V51: =IF($A51="","",IF(N51=0,"",(N51-Q51)/N51)) | W51: 账户年检完成率 100%；票据背书抽查发现 1 处瑕疵
M52: =IF($A52="","",ROUND(MAX(SUMPRODUCT(H52:L52,IFERROR(VLOOKUP($C52,参数配置!$A$26:$F$38,{2,3,4,5,6},FALSE),VLOOKUP(参数配置!$A$26,参数配置!$A$26:$F$38,{2,3,4,5,6},FALSE))),参数配置!$E$13*MAX(H52:L52)),2)) | N52: =IF($A52="","",ROUND(G52*M52,2)) | O52: =IF($A52="","",IF(COUNTIFS(控制措施表!$B:$B,$A52,控制措施表!$C:$C,$F52,控制措施表!$F:$F,"是")=0,IF(COUNTIFS(控制措施表!$B:$B,$A52,控制措施表!$C:$C,$F52)=0,"",MINIFS(控制措施表!$E:$E,控制措施表!$B:$B,$A52,控制措施表!$C:$C,$F52)),MINIFS(控制措施表!$E:$E,控制措施表!$B:$B,$A52,控制措施表!$C:$C,$F52,控制措施表!$F:$F,"是"))) | P52: =IF($A52="","",IF(N52="",0,VLOOKUP(N52,参数配置!$D$4:$E$8,2,FALSE))) | Q52: =IF($A52="","",ROUND(O52*(1-P52),2)) | R52: =IF($A52="","",IF(Q52>=参数配置!$B$12,"极高",IF(Q52>=参数配置!$B$13,"高",IF(Q52>=参数配置!$B$14,"中",IF(Q52>=参数配置!$B$15,"低","极低"))))) | S52: =IF($A52="","",ROUND(M52,0)) | T52: =IF($A52="","",ROUND(N52,0)) | U52: =IF($A52="","",IF(R52="极高","每年必审",IF(R52="高","每年审计",IF(R52="中","两年一轮","按需抽查")))) | V52: =IF($A52="","",IF(N52=0,"",(N52-Q52)/N52))
M53: =IF($A53="","",ROUND(MAX(SUMPRODUCT(H53:L53,IFERROR(VLOOKUP($C53,参数配置!$A$26:$F$38,{2,3,4,5,6},FALSE),VLOOKUP(参数配置!$A$26,参数配置!$A$26:$F$38,{2,3,4,5,6},FALSE))),参数配置!$E$13*MAX(H53:L53)),2)) | N53: =IF($A53="","",ROUND(G53*M53,2)) | O53: =IF($A53="","",IF(COUNTIFS(控制措施表!$B:$B,$A53,控制措施表!$C:$C,$F53,控制措施表!$F:$F,"是")=0,IF(COUNTIFS(控制措施表!$B:$B,$A53,控制措施表!$C:$C,$F53)=0,"",MINIFS(控制措施表!$E:$E,控制措施表!$B:$B,$A53,控制措施表!$C:$C,$F53)),MINIFS(控制措施表!$E:$E,控制措施表!$B:$B,$A53,控制措施表!$C:$C,$F53,控制措施表!$F:$F,"是"))) | P53: =IF($A53="","",IF(N53="",0,VLOOKUP(N53,参数配置!$D$4:$E$8,2,FALSE))) | Q53: =IF($A53="","",ROUND(O53*(1-P53),2)) | R53: =IF($A53="","",IF(Q53>=参数配置!$B$12,"极高",IF(Q53>=参数配置!$B$13,"高",IF(Q53>=参数配置!$B$14,"中",IF(Q53>=参数配置!$B$15,"低","极低"))))) | S53: =IF($A53="","",ROUND(M53,0)) | T53: =IF($A53="","",ROUND(N53,0)) | U53: =IF($A53="","",IF(R53="极高","每年必审",IF(R53="高","每年审计",IF(R53="中","两年一轮","按需抽查")))) | V53: =IF($A53="","",IF(N53=0,"",(N53-Q53)/N53))
M54: =IF($A54="","",ROUND(MAX(SUMPRODUCT(H54:L54,IFERROR(VLOOKUP($C54,参数配置!$A$26:$F$38,{2,3,4,5,6},FALSE),VLOOKUP(参数配置!$A$26,参数配置!$A$26:$F$38,{2,3,4,5,6},FALSE))),参数配置!$E$13*MAX(H54:L54)),2)) | N54: =IF($A54="","",ROUND(G54*M54,2)) | O54: =IF($A54="","",IF(COUNTIFS(控制措施表!$B:$B,$A54,控制措施表!$C:$C,$F54,控制措施表!$F:$F,"是")=0,IF(COUNTIFS(控制措施表!$B:$B,$A54,控制措施表!$C:$C,$F54)=0,"",MINIFS(控制措施表!$E:$E,控制措施表!$B:$B,$A54,控制措施表!$C:$C,$F54)),MINIFS(控制措施表!$E:$E,控制措施表!$B:$B,$A54,控制措施表!$C:$C,$F54,控制措施表!$F:$F,"是"))) | P54: =IF($A54="","",IF(N54="",0,VLOOKUP(N54,参数配置!$D$4:$E$8,2,FALSE))) | Q54: =IF($A54="","",ROUND(O54*(1-P54),2)) | R54: =IF($A54="","",IF(Q54>=参数配置!$B$12,"极高",IF(Q54>=参数配置!$B$13,"高",IF(Q54>=参数配置!$B$14,"中",IF(Q54>=参数配置!$B$15,"低","极低"))))) | S54: =IF($A54="","",ROUND(M54,0)) | T54: =IF($A54="","",ROUND(N54,0)) | U54: =IF($A54="","",IF(R54="极高","每年必审",IF(R54="高","每年审计",IF(R54="中","两年一轮","按需抽查")))) | V54: =IF($A54="","",IF(N54=0,"",(N54-Q54)/N54))
M55: =IF($A55="","",ROUND(MAX(SUMPRODUCT(H55:L55,IFERROR(VLOOKUP($C55,参数配置!$A$26:$F$38,{2,3,4,5,6},FALSE),VLOOKUP(参数配置!$A$26,参数配置!$A$26:$F$38,{2,3,4,5,6},FALSE))),参数配置!$E$13*MAX(H55:L55)),2)) | N55: =IF($A55="","",ROUND(G55*M55,2)) | O55: =IF($A55="","",IF(COUNTIFS(控制措施表!$B:$B,$A55,控制措施表!$C:$C,$F55,控制措施表!$F:$F,"是")=0,IF(COUNTIFS(控制措施表!$B:$B,$A55,控制措施表!$C:$C,$F55)=0,"",MINIFS(控制措施表!$E:$E,控制措施表!$B:$B,$A55,控制措施表!$C:$C,$F55)),MINIFS(控制措施表!$E:$E,控制措施表!$B:$B,$A55,控制措施表!$C:$C,$F55,控制措施表!$F:$F,"是"))) | P55: =IF($A55="","",IF(N55="",0,VLOOKUP(N55,参数配置!$D$4:$E$8,2,FALSE))) | Q55: =IF($A55="","",ROUND(O55*(1-P55),2)) | R55: =IF($A55="","",IF(Q55>=参数配置!$B$12,"极高",IF(Q55>=参数配置!$B$13,"高",IF(Q55>=参数配置!$B$14,"中",IF(Q55>=参数配置!$B$15,"低","极低"))))) | S55: =IF($A55="","",ROUND(M55,0)) | T55: =IF($A55="","",ROUND(N55,0)) | U55: =IF($A55="","",IF(R55="极高","每年必审",IF(R55="高","每年审计",IF(R55="中","两年一轮","按需抽查")))) | V55: =IF($A55="","",IF(N55=0,"",(N55-Q55)/N55))
M56: =IF($A56="","",ROUND(MAX(SUMPRODUCT(H56:L56,IFERROR(VLOOKUP($C56,参数配置!$A$26:$F$38,{2,3,4,5,6},FALSE),VLOOKUP(参数配置!$A$26,参数配置!$A$26:$F$38,{2,3,4,5,6},FALSE))),参数配置!$E$13*MAX(H56:L56)),2)) | N56: =IF($A56="","",ROUND(G56*M56,2)) | O56: =IF($A56="","",IF(COUNTIFS(控制措施表!$B:$B,$A56,控制措施表!$C:$C,$F56,控制措施表!$F:$F,"是")=0,IF(COUNTIFS(控制措施表!$B:$B,$A56,控制措施表!$C:$C,$F56)=0,"",MINIFS(控制措施表!$E:$E,控制措施表!$B:$B,$A56,控制措施表!$C:$C,$F56)),MINIFS(控制措施表!$E:$E,控制措施表!$B:$B,$A56,控制措施表!$C:$C,$F56,控制措施表!$F:$F,"是"))) | P56: =IF($A56="","",IF(N56="",0,VLOOKUP(N56,参数配置!$D$4:$E$8,2,FALSE))) | Q56: =IF($A56="","",ROUND(O56*(1-P56),2)) | R56: =IF($A56="","",IF(Q56>=参数配置!$B$12,"极高",IF(Q56>=参数配置!$B$13,"高",IF(Q56>=参数配置!$B$14,"中",IF(Q56>=参数配置!$B$15,"低","极低"))))) | S56: =IF($A56="","",ROUND(M56,0)) | T56: =IF($A56="","",ROUND(N56,0)) | U56: =IF($A56="","",IF(R56="极高","每年必审",IF(R56="高","每年审计",IF(R56="中","两年一轮","按需抽查")))) | V56: =IF($A56="","",IF(N56=0,"",(N56-Q56)/N56))
M57: =IF($A57="","",ROUND(MAX(SUMPRODUCT(H57:L57,IFERROR(VLOOKUP($C57,参数配置!$A$26:$F$38,{2,3,4,5,6},FALSE),VLOOKUP(参数配置!$A$26,参数配置!$A$26:$F$38,{2,3,4,5,6},FALSE))),参数配置!$E$13*MAX(H57:L57)),2)) | N57: =IF($A57="","",ROUND(G57*M57,2)) | O57: =IF($A57="","",IF(COUNTIFS(控制措施表!$B:$B,$A57,控制措施表!$C:$C,$F57,控制措施表!$F:$F,"是")=0,IF(COUNTIFS(控制措施表!$B:$B,$A57,控制措施表!$C:$C,$F57)=0,"",MINIFS(控制措施表!$E:$E,控制措施表!$B:$B,$A57,控制措施表!$C:$C,$F57)),MINIFS(控制措施表!$E:$E,控制措施表!$B:$B,$A57,控制措施表!$C:$C,$F57,控制措施表!$F:$F,"是"))) | P57: =IF($A57="","",IF(N57="",0,VLOOKUP(N57,参数配置!$D$4:$E$8,2,FALSE))) | Q57: =IF($A57="","",ROUND(O57*(1-P57),2)) | R57: =IF($A57="","",IF(Q57>=参数配置!$B$12,"极高",IF(Q57>=参数配置!$B$13,"高",IF(Q57>=参数配置!$B$14,"中",IF(Q57>=参数配置!$B$15,"低","极低"))))) | S57: =IF($A57="","",ROUND(M57,0)) | T57: =IF($A57="","",ROUND(N57,0)) | U57: =IF($A57="","",IF(R57="极高","每年必审",IF(R57="高","每年审计",IF(R57="中","两年一轮","按需抽查")))) | V57: =IF($A57="","",IF(N57=0,"",(N57-Q57)/N57))
M58: =IF($A58="","",ROUND(MAX(SUMPRODUCT(H58:L58,IFERROR(VLOOKUP($C58,参数配置!$A$26:$F$38,{2,3,4,5,6},FALSE),VLOOKUP(参数配置!$A$26,参数配置!$A$26:$F$38,{2,3,4,5,6},FALSE))),参数配置!$E$13*MAX(H58:L58)),2)) | N58: =IF($A58="","",ROUND(G58*M58,2)) | O58: =IF($A58="","",IF(COUNTIFS(控制措施表!$B:$B,$A58,控制措施表!$C:$C,$F58,控制措施表!$F:$F,"是")=0,IF(COUNTIFS(控制措施表!$B:$B,$A58,控制措施表!$C:$C,$F58)=0,"",MINIFS(控制措施表!$E:$E,控制措施表!$B:$B,$A58,控制措施表!$C:$C,$F58)),MINIFS(控制措施表!$E:$E,控制措施表!$B:$B,$A58,控制措施表!$C:$C,$F58,控制措施表!$F:$F,"是"))) | P58: =IF($A58="","",IF(N58="",0,VLOOKUP(N58,参数配置!$D$4:$E$8,2,FALSE))) | Q58: =IF($A58="","",ROUND(O58*(1-P58),2)) | R58: =IF($A58="","",IF(Q58>=参数配置!$B$12,"极高",IF(Q58>=参数配置!$B$13,"高",IF(Q58>=参数配置!$B$14,"中",IF(Q58>=参数配置!$B$15,"低","极低"))))) | S58: =IF($A58="","",ROUND(M58,0)) | T58: =IF($A58="","",ROUND(N58,0)) | U58: =IF($A58="","",IF(R58="极高","每年必审",IF(R58="高","每年审计",IF(R58="中","两年一轮","按需抽查")))) | V58: =IF($A58="","",IF(N58=0,"",(N58-Q58)/N58))
M59: =IF($A59="","",ROUND(MAX(SUMPRODUCT(H59:L59,IFERROR(VLOOKUP($C59,参数配置!$A$26:$F$38,{2,3,4,5,6},FALSE),VLOOKUP(参数配置!$A$26,参数配置!$A$26:$F$38,{2,3,4,5,6},FALSE))),参数配置!$E$13*MAX(H59:L59)),2)) | N59: =IF($A59="","",ROUND(G59*M59,2)) | O59: =IF($A59="","",IF(COUNTIFS(控制措施表!$B:$B,$A59,控制措施表!$C:$C,$F59,控制措施表!$F:$F,"是")=0,IF(COUNTIFS(控制措施表!$B:$B,$A59,控制措施表!$C:$C,$F59)=0,"",MINIFS(控制措施表!$E:$E,控制措施表!$B:$B,$A59,控制措施表!$C:$C,$F59)),MINIFS(控制措施表!$E:$E,控制措施表!$B:$B,$A59,控制措施表!$C:$C,$F59,控制措施表!$F:$F,"是"))) | P59: =IF($A59="","",IF(N59="",0,VLOOKUP(N59,参数配置!$D$4:$E$8,2,FALSE))) | Q59: =IF($A59="","",ROUND(O59*(1-P59),2)) | R59: =IF($A59="","",IF(Q59>=参数配置!$B$12,"极高",IF(Q59>=参数配置!$B$13,"高",IF(Q59>=参数配置!$B$14,"中",IF(Q59>=参数配置!$B$15,"低","极低"))))) | S59: =IF($A59="","",ROUND(M59,0)) | T59: =IF($A59="","",ROUND(N59,0)) | U59: =IF($A59="","",IF(R59="极高","每年必审",IF(R59="高","每年审计",IF(R59="中","两年一轮","按需抽查")))) | V59: =IF($A59="","",IF(N59=0,"",(N59-Q59)/N59))
M60: =IF($A60="","",ROUND(MAX(SUMPRODUCT(H60:L60,IFERROR(VLOOKUP($C60,参数配置!$A$26:$F$38,{2,3,4,5,6},FALSE),VLOOKUP(参数配置!$A$26,参数配置!$A$26:$F$38,{2,3,4,5,6},FALSE))),参数配置!$E$13*MAX(H60:L60)),2)) | N60: =IF($A60="","",ROUND(G60*M60,2)) | O60: =IF($A60="","",IF(COUNTIFS(控制措施表!$B:$B,$A60,控制措施表!$C:$C,$F60,控制措施表!$F:$F,"是")=0,IF(COUNTIFS(控制措施表!$B:$B,$A60,控制措施表!$C:$C,$F60)=0,"",MINIFS(控制措施表!$E:$E,控制措施表!$B:$B,$A60,控制措施表!$C:$C,$F60)),MINIFS(控制措施表!$E:$E,控制措施表!$B:$B,$A60,控制措施表!$C:$C,$F60,控制措施表!$F:$F,"是"))) | P60: =IF($A60="","",IF(N60="",0,VLOOKUP(N60,参数配置!$D$4:$E$8,2,FALSE))) | Q60: =IF($A60="","",ROUND(O60*(1-P60),2)) | R60: =IF($A60="","",IF(Q60>=参数配置!$B$12,"极高",IF(Q60>=参数配置!$B$13,"高",IF(Q60>=参数配置!$B$14,"中",IF(Q60>=参数配置!$B$15,"低","极低"))))) | S60: =IF($A60="","",ROUND(M60,0)) | T60: =IF($A60="","",ROUND(N60,0)) | U60: =IF($A60="","",IF(R60="极高","每年必审",IF(R60="高","每年审计",IF(R60="中","两年一轮","按需抽查")))) | V60: =IF($A60="","",IF(N60=0,"",(N60-Q60)/N60))
M61: =IF($A61="","",ROUND(MAX(SUMPRODUCT(H61:L61,IFERROR(VLOOKUP($C61,参数配置!$A$26:$F$38,{2,3,4,5,6},FALSE),VLOOKUP(参数配置!$A$26,参数配置!$A$26:$F$38,{2,3,4,5,6},FALSE))),参数配置!$E$13*MAX(H61:L61)),2)) | N61: =IF($A61="","",ROUND(G61*M61,2)) | O61: =IF($A61="","",IF(COUNTIFS(控制措施表!$B:$B,$A61,控制措施表!$C:$C,$F61,控制措施表!$F:$F,"是")=0,IF(COUNTIFS(控制措施表!$B:$B,$A61,控制措施表!$C:$C,$F61)=0,"",MINIFS(控制措施表!$E:$E,控制措施表!$B:$B,$A61,控制措施表!$C:$C,$F61)),MINIFS(控制措施表!$E:$E,控制措施表!$B:$B,$A61,控制措施表!$C:$C,$F61,控制措施表!$F:$F,"是"))) | P61: =IF($A61="","",IF(N61="",0,VLOOKUP(N61,参数配置!$D$4:$E$8,2,FALSE))) | Q61: =IF($A61="","",ROUND(O61*(1-P61),2)) | R61: =IF($A61="","",IF(Q61>=参数配置!$B$12,"极高",IF(Q61>=参数配置!$B$13,"高",IF(Q61>=参数配置!$B$14,"中",IF(Q61>=参数配置!$B$15,"低","极低"))))) | S61: =IF($A61="","",ROUND(M61,0)) | T61: =IF($A61="","",ROUND(N61,0)) | U61: =IF($A61="","",IF(R61="极高","每年必审",IF(R61="高","每年审计",IF(R61="中","两年一轮","按需抽查")))) | V61: =IF($A61="","",IF(N61=0,"",(N61-Q61)/N61))
M62: =IF($A62="","",ROUND(MAX(SUMPRODUCT(H62:L62,IFERROR(VLOOKUP($C62,参数配置!$A$26:$F$38,{2,3,4,5,6},FALSE),VLOOKUP(参数配置!$A$26,参数配置!$A$26:$F$38,{2,3,4,5,6},FALSE))),参数配置!$E$13*MAX(H62:L62)),2)) | N62: =IF($A62="","",ROUND(G62*M62,2)) | O62: =IF($A62="","",IF(COUNTIFS(控制措施表!$B:$B,$A62,控制措施表!$C:$C,$F62,控制措施表!$F:$F,"是")=0,IF(COUNTIFS(控制措施表!$B:$B,$A62,控制措施表!$C:$C,$F62)=0,"",MINIFS(控制措施表!$E:$E,控制措施表!$B:$B,$A62,控制措施表!$C:$C,$F62)),MINIFS(控制措施表!$E:$E,控制措施表!$B:$B,$A62,控制措施表!$C:$C,$F62,控制措施表!$F:$F,"是"))) | P62: =IF($A62="","",IF(N62="",0,VLOOKUP(N62,参数配置!$D$4:$E$8,2,FALSE))) | Q62: =IF($A62="","",ROUND(O62*(1-P62),2)) | R62: =IF($A62="","",IF(Q62>=参数配置!$B$12,"极高",IF(Q62>=参数配置!$B$13,"高",IF(Q62>=参数配置!$B$14,"中",IF(Q62>=参数配置!$B$15,"低","极低"))))) | S62: =IF($A62="","",ROUND(M62,0)) | T62: =IF($A62="","",ROUND(N62,0)) | U62: =IF($A62="","",IF(R62="极高","每年必审",IF(R62="高","每年审计",IF(R62="中","两年一轮","按需抽查")))) | V62: =IF($A62="","",IF(N62=0,"",(N62-Q62)/N62))
M63: =IF($A63="","",ROUND(MAX(SUMPRODUCT(H63:L63,IFERROR(VLOOKUP($C63,参数配置!$A$26:$F$38,{2,3,4,5,6},FALSE),VLOOKUP(参数配置!$A$26,参数配置!$A$26:$F$38,{2,3,4,5,6},FALSE))),参数配置!$E$13*MAX(H63:L63)),2)) | N63: =IF($A63="","",ROUND(G63*M63,2)) | O63: =IF($A63="","",IF(COUNTIFS(控制措施表!$B:$B,$A63,控制措施表!$C:$C,$F63,控制措施表!$F:$F,"是")=0,IF(COUNTIFS(控制措施表!$B:$B,$A63,控制措施表!$C:$C,$F63)=0,"",MINIFS(控制措施表!$E:$E,控制措施表!$B:$B,$A63,控制措施表!$C:$C,$F63)),MINIFS(控制措施表!$E:$E,控制措施表!$B:$B,$A63,控制措施表!$C:$C,$F63,控制措施表!$F:$F,"是"))) | P63: =IF($A63="","",IF(N63="",0,VLOOKUP(N63,参数配置!$D$4:$E$8,2,FALSE))) | Q63: =IF($A63="","",ROUND(O63*(1-P63),2)) | R63: =IF($A63="","",IF(Q63>=参数配置!$B$12,"极高",IF(Q63>=参数配置!$B$13,"高",IF(Q63>=参数配置!$B$14,"中",IF(Q63>=参数配置!$B$15,"低","极低"))))) | S63: =IF($A63="","",ROUND(M63,0)) | T63: =IF($A63="","",ROUND(N63,0)) | U63: =IF($A63="","",IF(R63="极高","每年必审",IF(R63="高","每年审计",IF(R63="中","两年一轮","按需抽查")))) | V63: =IF($A63="","",IF(N63=0,"",(N63-Q63)/N63))
... M203: =IF($A203="","",ROUND(MAX(SUMPRODUCT(H203:L203,IFERROR(VLOOKUP($C203,参数配置!$A$26:$F$38,{2,3,4,5,6},FALSE),VLOOKUP(参数配置!$A$26,参数配置!$A$26:$F$38,{2,3,4,5,6},FALSE))),参数配置!$E$13*MAX(H203:L203)),2)) | N203: =IF($A203="","",ROUND(G203*M203,2)) | O203: =IF($A203="","",IF(COUNTIFS(控制措施表!$B:$B,$A203,控制措施表!$C:$C,$F203,控制措施表!$F:$F,"是")=0,IF(COUNTIFS(控制措施表!$B:$B,$A203,控制措施表!$C:$C,$F203)=0,"",MINIFS(控制措施表!$E:$E,控制措施表!$B:$B,$A203,控制措施表!$C:$C,$F203)),MINIFS(控制措施表!$E:$E,控制措施表!$B:$B,$A203,控制措施表!$C:$C,$F203,控制措施表!$F:$F,"是"))) | P203: =IF($A203="","",IF(N203="",0,VLOOKUP(N203,参数配置!$D$4:$E$8,2,FALSE))) | Q203: =IF($A203="","",ROUND(O203*(1-P203),2)) | R203: =IF($A203="","",IF(Q203>=参数配置!$B$12,"极高",IF(Q203>=参数配置!$B$13,"高",IF(Q203>=参数配置!$B$14,"中",IF(Q203>=参数配置!$B$15,"低","极低"))))) | S203: =IF($A203="","",ROUND(M203,0)) | T203: =IF($A203="","",ROUND(N203,0)) | U203: =IF($A203="","",IF(R203="极高","每年必审",IF(R203="高","每年审计",IF(R203="中","两年一轮","按需抽查")))) | V203: =IF($A203="","",IF(N203=0,"",(N203-Q203)/N203))

Sheet 控制措施表
A1: 控制措施表（每条风险可挂多条控制点；剩余风险按“关键控制最弱分”折减，未标记关键则按全部控制点最弱分）
A3: 控制编号 | B3: 关联风险编号 | C3: 评估期间 | D3: 控制点描述 | E3: 有效性评分 (1-5) | F3: 关键控制
A4: C001 | B4: R001 | C4: 2026H1 | D4: 预算系统刚性拦截超标报销 | E4: 4 | F4: 否
A5: C002 | B5: R001 | C5: 2026H1 | D5: 大额报销双人复核并抽凭 | E5: 3 | F5: 是
A6: C003 | B6: R002 | C6: 2026H1 | D6: 季度收入截止测试程序 | E6: 4 | F6: 是
A7: C004 | B7: R002 | C7: 2026H1 | D7: 业财对账自动化月度核对 | E7: 3 | F7: 否
A8: C005 | B8: R003 | C8: 2026H1 | D8: 审批权限矩阵嵌入 OA 硬控制 | E8: 4 | F8: 否
A9: C006 | B9: R003 | C9: 2026H1 | D9: 网银支付双人复核 | E9: 5 | F9: 是
A10: C007 | B10: R003 | C10: 2026H1 | D10: 内审资金专项检查 | E10: 3 | F10: 否
A11: C008 | B11: R004 | C11: 2026H1 | D11: 全流程电子化招投标平台留痕 | E11: 4 | F11: 是
A12: C009 | B12: R004 | C12: 2026H1 | D12: 供应商关联关系申报承诺 | E12: 3 | F12: 否
A13: C010 | B13: R004 | C13: 2026H1 | D13: 评标专家随机抽取 | E13: 4 | F13: 否
A14: C011 | B14: R005 | C14: 2026H1 | D14: 标准合同模板库加法务会签 | E14: 4 | F14: 是
A15: C012 | B15: R005 | C15: 2026H1 | D15: 履约台账跟踪预警 | E15: 3 | F15: 否
... A66: C063 | B66: R024 | C66: 2025H2 | D66: 账户手工登记簿 | E66: 2 | F66: 是

Sheet 热力图
A1: 风险热力图（可能性 × 综合影响）
B3: 评估期间筛选： | C3: 2026H1
B5: ① 固有热力图 —— 格内数字为落入该格的风险数量
B6: 可能性＼影响 | C6: 1 | D6: 2 | E6: 3 | F6: 4 | G6: 5
B7: 5 | C7: =COUNTIFS(风险登记册!$F$4:$F$203,IF($C$3="全部","<>",$C$3),风险登记册!$G$4:$G$203,$B7,风险登记册!$S$4:$S$203,C$6) | D7: =COUNTIFS(风险登记册!$F$4:$F$203,IF($C$3="全部","<>",$C$3),风险登记册!$G$4:$G$203,$B7,风险登记册!$S$4:$S$203,D$6) | E7: =COUNTIFS(风险登记册!$F$4:$F$203,IF($C$3="全部","<>",$C$3),风险登记册!$G$4:$G$203,$B7,风险登记册!$S$4:$S$203,E$6) | F7: =COUNTIFS(风险登记册!$F$4:$F$203,IF($C$3="全部","<>",$C$3),风险登记册!$G$4:$G$203,$B7,风险登记册!$S$4:$S$203,F$6) | G7: =COUNTIFS(风险登记册!$F$4:$F$203,IF($C$3="全部","<>",$C$3),风险登记册!$G$4:$G$203,$B7,风险登记册!$S$4:$S$203,G$6)
B8: 4 | C8: =COUNTIFS(风险登记册!$F$4:$F$203,IF($C$3="全部","<>",$C$3),风险登记册!$G$4:$G$203,$B8,风险登记册!$S$4:$S$203,C$6) | D8: =COUNTIFS(风险登记册!$F$4:$F$203,IF($C$3="全部","<>",$C$3),风险登记册!$G$4:$G$203,$B8,风险登记册!$S$4:$S$203,D$6) | E8: =COUNTIFS(风险登记册!$F$4:$F$203,IF($C$3="全部","<>",$C$3),风险登记册!$G$4:$G$203,$B8,风险登记册!$S$4:$S$203,E$6) | F8: =COUNTIFS(风险登记册!$F$4:$F$203,IF($C$3="全部","<>",$C$3),风险登记册!$G$4:$G$203,$B8,风险登记册!$S$4:$S$203,F$6) | G8: =COUNTIFS(风险登记册!$F$4:$F$203,IF($C$3="全部","<>",$C$3),风险登记册!$G$4:$G$203,$B8,风险登记册!$S$4:$S$203,G$6)
B9: 3 | C9: =COUNTIFS(风险登记册!$F$4:$F$203,IF($C$3="全部","<>",$C$3),风险登记册!$G$4:$G$203,$B9,风险登记册!$S$4:$S$203,C$6) | D9: =COUNTIFS(风险登记册!$F$4:$F$203,IF($C$3="全部","<>",$C$3),风险登记册!$G$4:$G$203,$B9,风险登记册!$S$4:$S$203,D$6) | E9: =COUNTIFS(风险登记册!$F$4:$F$203,IF($C$3="全部","<>",$C$3),风险登记册!$G$4:$G$203,$B9,风险登记册!$S$4:$S$203,E$6) | F9: =COUNTIFS(风险登记册!$F$4:$F$203,IF($C$3="全部","<>",$C$3),风险登记册!$G$4:$G$203,$B9,风险登记册!$S$4:$S$203,F$6) | G9: =COUNTIFS(风险登记册!$F$4:$F$203,IF($C$3="全部","<>",$C$3),风险登记册!$G$4:$G$203,$B9,风险登记册!$S$4:$S$203,G$6)
B10: 2 | C10: =COUNTIFS(风险登记册!$F$4:$F$203,IF($C$3="全部","<>",$C$3),风险登记册!$G$4:$G$203,$B10,风险登记册!$S$4:$S$203,C$6) | D10: =COUNTIFS(风险登记册!$F$4:$F$203,IF($C$3="全部","<>",$C$3),风险登记册!$G$4:$G$203,$B10,风险登记册!$S$4:$S$203,D$6) | E10: =COUNTIFS(风险登记册!$F$4:$F$203,IF($C$3="全部","<>",$C$3),风险登记册!$G$4:$G$203,$B10,风险登记册!$S$4:$S$203,E$6) | F10: =COUNTIFS(风险登记册!$F$4:$F$203,IF($C$3="全部","<>",$C$3),风险登记册!$G$4:$G$203,$B10,风险登记册!$S$4:$S$203,F$6) | G10: =COUNTIFS(风险登记册!$F$4:$F$203,IF($C$3="全部","<>",$C$3),风险登记册!$G$4:$G$203,$B10,风险登记册!$S$4:$S$203,G$6)
B11: 1 | C11: =COUNTIFS(风险登记册!$F$4:$F$203,IF($C$3="全部","<>",$C$3),风险登记册!$G$4:$G$203,$B11,风险登记册!$S$4:$S$203,C$6) | D11: =COUNTIFS(风险登记册!$F$4:$F$203,IF($C$3="全部","<>",$C$3),风险登记册!$G$4:$G$203,$B11,风险登记册!$S$4:$S$203,D$6) | E11: =COUNTIFS(风险登记册!$F$4:$F$203,IF($C$3="全部","<>",$C$3),风险登记册!$G$4:$G$203,$B11,风险登记册!$S$4:$S$203,E$6) | F11: =COUNTIFS(风险登记册!$F$4:$F$203,IF($C$3="全部","<>",$C$3),风险登记册!$G$4:$G$203,$B11,风险登记册!$S$4:$S$203,F$6) | G11: =COUNTIFS(风险登记册!$F$4:$F$203,IF($C$3="全部","<>",$C$3),风险登记册!$G$4:$G$203,$B11,风险登记册!$S$4:$S$203,G$6)
B13: ② 剩余热力图 —— 格内数字为该位置风险的剩余分均值（底色按均值联动阈值）
B14: 可能性＼影响 | C14: 1 | D14: 2 | E14: 3 | F14: 4 | G14: 5
B15: 5 | C15: =IFERROR(AVERAGEIFS(风险登记册!$Q$4:$Q$203,风险登记册!$F$4:$F$203,IF($C$3="全部","<>",$C$3),风险登记册!$G$4:$G$203,$B15,风险登记册!$S$4:$S$203,C$14),"") | D15: =IFERROR(AVERAGEIFS(风险登记册!$Q$4:$Q$203,风险登记册!$F$4:$F$203,IF($C$3="全部","<>",$C$3),风险登记册!$G$4:$G$203,$B15,风险登记册!$S$4:$S$203,D$14),"") | E15: =IFERROR(AVERAGEIFS(风险登记册!$Q$4:$Q$203,风险登记册!$F$4:$F$203,IF($C$3="全部","<>",$C$3),风险登记册!$G$4:$G$203,$B15,风险登记册!$S$4:$S$203,E$14),"") | F15: =IFERROR(AVERAGEIFS(风险登记册!$Q$4:$Q$203,风险登记册!$F$4:$F$203,IF($C$3="全部","<>",$C$3),风险登记册!$G$4:$G$203,$B15,风险登记册!$S$4:$S$203,F$14),"") | G15: =IFERROR(AVERAGEIFS(风险登记册!$Q$4:$Q$203,风险登记册!$F$4:$F$203,IF($C$3="全部","<>",$C$3),风险登记册!$G$4:$G$203,$B15,风险登记册!$S$4:$S$203,G$14),"")
B16: 4 | C16: =IFERROR(AVERAGEIFS(风险登记册!$Q$4:$Q$203,风险登记册!$F$4:$F$203,IF($C$3="全部","<>",$C$3),风险登记册!$G$4:$G$203,$B16,风险登记册!$S$4:$S$203,C$14),"") | D16: =IFERROR(AVERAGEIFS(风险登记册!$Q$4:$Q$203,风险登记册!$F$4:$F$203,IF($C$3="全部","<>",$C$3),风险登记册!$G$4:$G$203,$B16,风险登记册!$S$4:$S$203,D$14),"") | E16: =IFERROR(AVERAGEIFS(风险登记册!$Q$4:$Q$203,风险登记册!$F$4:$F$203,IF($C$3="全部","<>",$C$3),风险登记册!$G$4:$G$203,$B16,风险登记册!$S$4:$S$203,E$14),"") | F16: =IFERROR(AVERAGEIFS(风险登记册!$Q$4:$Q$203,风险登记册!$F$4:$F$203,IF($C$3="全部","<>",$C$3),风险登记册!$G$4:$G$203,$B16,风险登记册!$S$4:$S$203,F$14),"") | G16: =IFERROR(AVERAGEIFS(风险登记册!$Q$4:$Q$203,风险登记册!$F$4:$F$203,IF($C$3="全部","<>",$C$3),风险登记册!$G$4:$G$203,$B16,风险登记册!$S$4:$S$203,G$14),"")
B17: 3 | C17: =IFERROR(AVERAGEIFS(风险登记册!$Q$4:$Q$203,风险登记册!$F$4:$F$203,IF($C$3="全部","<>",$C$3),风险登记册!$G$4:$G$203,$B17,风险登记册!$S$4:$S$203,C$14),"") | D17: =IFERROR(AVERAGEIFS(风险登记册!$Q$4:$Q$203,风险登记册!$F$4:$F$203,IF($C$3="全部","<>",$C$3),风险登记册!$G$4:$G$203,$B17,风险登记册!$S$4:$S$203,D$14),"") | E17: =IFERROR(AVERAGEIFS(风险登记册!$Q$4:$Q$203,风险登记册!$F$4:$F$203,IF($C$3="全部","<>",$C$3),风险登记册!$G$4:$G$203,$B17,风险登记册!$S$4:$S$203,E$14),"") | F17: =IFERROR(AVERAGEIFS(风险登记册!$Q$4:$Q$203,风险登记册!$F$4:$F$203,IF($C$3="全部","<>",$C$3),风险登记册!$G$4:$G$203,$B17,风险登记册!$S$4:$S$203,F$14),"") | G17: =IFERROR(AVERAGEIFS(风险登记册!$Q$4:$Q$203,风险登记册!$F$4:$F$203,IF($C$3="全部","<>",$C$3),风险登记册!$G$4:$G$203,$B17,风险登记册!$S$4:$S$203,G$14),"")
B18: 2 | C18: =IFERROR(AVERAGEIFS(风险登记册!$Q$4:$Q$203,风险登记册!$F$4:$F$203,IF($C$3="全部","<>",$C$3),风险登记册!$G$4:$G$203,$B18,风险登记册!$S$4:$S$203,C$14),"") | D18: =IFERROR(AVERAGEIFS(风险登记册!$Q$4:$Q$203,风险登记册!$F$4:$F$203,IF($C$3="全部","<>",$C$3),风险登记册!$G$4:$G$203,$B18,风险登记册!$S$4:$S$203,D$14),"") | E18: =IFERROR(AVERAGEIFS(风险登记册!$Q$4:$Q$203,风险登记册!$F$4:$F$203,IF($C$3="全部","<>",$C$3),风险登记册!$G$4:$G$203,$B18,风险登记册!$S$4:$S$203,E$14),"") | F18: =IFERROR(AVERAGEIFS(风险登记册!$Q$4:$Q$203,风险登记册!$F$4:$F$203,IF($C$3="全部","<>",$C$3),风险登记册!$G$4:$G$203,$B18,风险登记册!$S$4:$S$203,F$14),"") | G18: =IFERROR(AVERAGEIFS(风险登记册!$Q$4:$Q$203,风险登记册!$F$4:$F$203,IF($C$3="全部","<>",$C$3),风险登记册!$G$4:$G$203,$B18,风险登记册!$S$4:$S$203,G$14),"")
B19: 1 | C19: =IFERROR(AVERAGEIFS(风险登记册!$Q$4:$Q$203,风险登记册!$F$4:$F$203,IF($C$3="全部","<>",$C$3),风险登记册!$G$4:$G$203,$B19,风险登记册!$S$4:$S$203,C$14),"") | D19: =IFERROR(AVERAGEIFS(风险登记册!$Q$4:$Q$203,风险登记册!$F$4:$F$203,IF($C$3="全部","<>",$C$3),风险登记册!$G$4:$G$203,$B19,风险登记册!$S$4:$S$203,D$14),"") | E19: =IFERROR(AVERAGEIFS(风险登记册!$Q$4:$Q$203,风险登记册!$F$4:$F$203,IF($C$3="全部","<>",$C$3),风险登记册!$G$4:$G$203,$B19,风险登记册!$S$4:$S$203,E$14),"") | F19: =IFERROR(AVERAGEIFS(风险登记册!$Q$4:$Q$203,风险登记册!$F$4:$F$203,IF($C$3="全部","<>",$C$3),风险登记册!$G$4:$G$203,$B19,风险登记册!$S$4:$S$203,F$14),"") | G19: =IFERROR(AVERAGEIFS(风险登记册!$Q$4:$Q$203,风险登记册!$F$4:$F$203,IF($C$3="全部","<>",$C$3),风险登记册!$G$4:$G$203,$B19,风险登记册!$S$4:$S$203,G$14),"")
B21: 图例
C22: 极高 | E22: 高 | G22: 中
C23: 低 | E23: 极低
B25: 说明：固有矩阵定位＝(发生可能性, 综合影响取整)；剩余矩阵同一坐标展示控制后的平均剩余分。逐条风险的精确剩余分见「汇总与优先级」页。

Sheet 汇总与优先级
A1: 汇总统计与年度审计优先级清单
A2: 评估期间（联动热力图页）： | B2: =热力图!$C$3
A4: 一、领域汇总
A5: 领域 | B5: 风险数 | C5: 平均剩余分 | D5: 最高剩余分 | E5: 极高数 | F5: 高数 | G5: 平均控制挽回率
A6: 战略与投资 | B6: =COUNTIFS(风险登记册!$C$4:$C$203,$A6,风险登记册!$F$4:$F$203,IF($B$2="全部","<>",$B$2)) | C6: =IFERROR(ROUND(AVERAGEIFS(风险登记册!$Q$4:$Q$203,风险登记册!$C$4:$C$203,$A6,风险登记册!$F$4:$F$203,IF($B$2="全部","<>",$B$2)),2),"—") | D6: =IFERROR(MAXIFS(风险登记册!$Q$4:$Q$203,风险登记册!$C$4:$C$203,$A6,风险登记册!$F$4:$F$203,IF($B$2="全部","<>",$B$2)),"—") | E6: =COUNTIFS(风险登记册!$R$4:$R$203,"极高",风险登记册!$C$4:$C$203,$A6,风险登记册!$F$4:$F$203,IF($B$2="全部","<>",$B$2)) | F6: =COUNTIFS(风险登记册!$R$4:$R$203,"高",风险登记册!$C$4:$C$203,$A6,风险登记册!$F$4:$F$203,IF($B$2="全部","<>",$B$2)) | G6: =IFERROR(AVERAGEIFS(风险登记册!$V$4:$V$203,风险登记册!$C$4:$C$203,$A6,风险登记册!$F$4:$F$203,IF($B$2="全部","<>",$B$2)),"—")
A7: 治理与决策 | B7: =COUNTIFS(风险登记册!$C$4:$C$203,$A7,风险登记册!$F$4:$F$203,IF($B$2="全部","<>",$B$2)) | C7: =IFERROR(ROUND(AVERAGEIFS(风险登记册!$Q$4:$Q$203,风险登记册!$C$4:$C$203,$A7,风险登记册!$F$4:$F$203,IF($B$2="全部","<>",$B$2)),2),"—") | D7: =IFERROR(MAXIFS(风险登记册!$Q$4:$Q$203,风险登记册!$C$4:$C$203,$A7,风险登记册!$F$4:$F$203,IF($B$2="全部","<>",$B$2)),"—") | E7: =COUNTIFS(风险登记册!$R$4:$R$203,"极高",风险登记册!$C$4:$C$203,$A7,风险登记册!$F$4:$F$203,IF($B$2="全部","<>",$B$2)) | F7: =COUNTIFS(风险登记册!$R$4:$R$203,"高",风险登记册!$C$4:$C$203,$A7,风险登记册!$F$4:$F$203,IF($B$2="全部","<>",$B$2)) | G7: =IFERROR(AVERAGEIFS(风险登记册!$V$4:$V$203,风险登记册!$C$4:$C$203,$A7,风险登记册!$F$4:$F$203,IF($B$2="全部","<>",$B$2)),"—")
A8: 资金活动 | B8: =COUNTIFS(风险登记册!$C$4:$C$203,$A8,风险登记册!$F$4:$F$203,IF($B$2="全部","<>",$B$2)) | C8: =IFERROR(ROUND(AVERAGEIFS(风险登记册!$Q$4:$Q$203,风险登记册!$C$4:$C$203,$A8,风险登记册!$F$4:$F$203,IF($B$2="全部","<>",$B$2)),2),"—") | D8: =IFERROR(MAXIFS(风险登记册!$Q$4:$Q$203,风险登记册!$C$4:$C$203,$A8,风险登记册!$F$4:$F$203,IF($B$2="全部","<>",$B$2)),"—") | E8: =COUNTIFS(风险登记册!$R$4:$R$203,"极高",风险登记册!$C$4:$C$203,$A8,风险登记册!$F$4:$F$203,IF($B$2="全部","<>",$B$2)) | F8: =COUNTIFS(风险登记册!$R$4:$R$203,"高",风险登记册!$C$4:$C$203,$A8,风险登记册!$F$4:$F$203,IF($B$2="全部","<>",$B$2)) | G8: =IFERROR(AVERAGEIFS(风险登记册!$V$4:$V$203,风险登记册!$C$4:$C$203,$A8,风险登记册!$F$4:$F$203,IF($B$2="全部","<>",$B$2)),"—")
A9: 财务报告与税务 | B9: =COUNTIFS(风险登记册!$C$4:$C$203,$A9,风险登记册!$F$4:$F$203,IF($B$2="全部","<>",$B$2)) | C9: =IFERROR(ROUND(AVERAGEIFS(风险登记册!$Q$4:$Q$203,风险登记册!$C$4:$C$203,$A9,风险登记册!$F$4:$F$203,IF($B$2="全部","<>",$B$2)),2),"—") | D9: =IFERROR(MAXIFS(风险登记册!$Q$4:$Q$203,风险登记册!$C$4:$C$203,$A9,风险登记册!$F$4:$F$203,IF($B$2="全部","<>",$B$2)),"—") | E9: =COUNTIFS(风险登记册!$R$4:$R$203,"极高",风险登记册!$C$4:$C$203,$A9,风险登记册!$F$4:$F$203,IF($B$2="全部","<>",$B$2)) | F9: =COUNTIFS(风险登记册!$R$4:$R$203,"高",风险登记册!$C$4:$C$203,$A9,风险登记册!$F$4:$F$203,IF($B$2="全部","<>",$B$2)) | G9: =IFERROR(AVERAGEIFS(风险登记册!$V$4:$V$203,风险登记册!$C$4:$C$203,$A9,风险登记册!$F$4:$F$203,IF($B$2="全部","<>",$B$2)),"—")
A10: 资产管理 | B10: =COUNTIFS(风险登记册!$C$4:$C$203,$A10,风险登记册!$F$4:$F$203,IF($B$2="全部","<>",$B$2)) | C10: =IFERROR(ROUND(AVERAGEIFS(风险登记册!$Q$4:$Q$203,风险登记册!$C$4:$C$203,$A10,风险登记册!$F$4:$F$203,IF($B$2="全部","<>",$B$2)),2),"—") | D10: =IFERROR(MAXIFS(风险登记册!$Q$4:$Q$203,风险登记册!$C$4:$C$203,$A10,风险登记册!$F$4:$F$203,IF($B$2="全部","<>",$B$2)),"—") | E10: =COUNTIFS(风险登记册!$R$4:$R$203,"极高",风险登记册!$C$4:$C$203,$A10,风险登记册!$F$4:$F$203,IF($B$2="全部","<>",$B$2)) | F10: =COUNTIFS(风险登记册!$R$4:$R$203,"高",风险登记册!$C$4:$C$203,$A10,风险登记册!$F$4:$F$203,IF($B$2="全部","<>",$B$2)) | G10: =IFERROR(AVERAGEIFS(风险登记册!$V$4:$V$203,风险登记册!$C$4:$C$203,$A10,风险登记册!$F$4:$F$203,IF($B$2="全部","<>",$B$2)),"—")
A11: 采购与外包 | B11: =COUNTIFS(风险登记册!$C$4:$C$203,$A11,风险登记册!$F$4:$F$203,IF($B$2="全部","<>",$B$2)) | C11: =IFERROR(ROUND(AVERAGEIFS(风险登记册!$Q$4:$Q$203,风险登记册!$C$4:$C$203,$A11,风险登记册!$F$4:$F$203,IF($B$2="全部","<>",$B$2)),2),"—") | D11: =IFERROR(MAXIFS(风险登记册!$Q$4:$Q$203,风险登记册!$C$4:$C$203,$A11,风险登记册!$F$4:$F$203,IF($B$2="全部","<>",$B$2)),"—") | E11: =COUNTIFS(风险登记册!$R$4:$R$203,"极高",风险登记册!$C$4:$C$203,$A11,风险登记册!$F$4:$F$203,IF($B$2="全部","<>",$B$2)) | F11: =COUNTIFS(风险登记册!$R$4:$R$203,"高",风险登记册!$C$4:$C$203,$A11,风险登记册!$F$4:$F$203,IF($B$2="全部","<>",$B$2)) | G11: =IFERROR(AVERAGEIFS(风险登记册!$V$4:$V$203,风险登记册!$C$4:$C$203,$A11,风险登记册!$F$4:$F$203,IF($B$2="全部","<>",$B$2)),"—")
A12: 合同管理 | B12: =COUNTIFS(风险登记册!$C$4:$C$203,$A12,风险登记册!$F$4:$F$203,IF($B$2="全部","<>",$B$2)) | C12: =IFERROR(ROUND(AVERAGEIFS(风险登记册!$Q$4:$Q$203,风险登记册!$C$4:$C$203,$A12,风险登记册!$F$4:$F$203,IF($B$2="全部","<>",$B$2)),2),"—") | D12: =IFERROR(MAXIFS(风险登记册!$Q$4:$Q$203,风险登记册!$C$4:$C$203,$A12,风险登记册!$F$4:$F$203,IF($B$2="全部","<>",$B$2)),"—") | E12: =COUNTIFS(风险登记册!$R$4:$R$203,"极高",风险登记册!$C$4:$C$203,$A12,风险登记册!$F$4:$F$203,IF($B$2="全部","<>",$B$2)) | F12: =COUNTIFS(风险登记册!$R$4:$R$203,"高",风险登记册!$C$4:$C$203,$A12,风险登记册!$F$4:$F$203,IF($B$2="全部","<>",$B$2)) | G12: =IFERROR(AVERAGEIFS(风险登记册!$V$4:$V$203,风险登记册!$C$4:$C$203,$A12,风险登记册!$F$4:$F$203,IF($B$2="全部","<>",$B$2)),"—")
A13: 工程项目 | B13: =COUNTIFS(风险登记册!$C$4:$C$203,$A13,风险登记册!$F$4:$F$203,IF($B$2="全部","<>",$B$2)) | C13: =IFERROR(ROUND(AVERAGEIFS(风险登记册!$Q$4:$Q$203,风险登记册!$C$4:$C$203,$A13,风险登记册!$F$4:$F$203,IF($B$2="全部","<>",$B$2)),2),"—") | D13: =IFERROR(MAXIFS(风险登记册!$Q$4:$Q$203,风险登记册!$C$4:$C$203,$A13,风险登记册!$F$4:$F$203,IF($B$2="全部","<>",$B$2)),"—") | E13: =COUNTIFS(风险登记册!$R$4:$R$203,"极高",风险登记册!$C$4:$C$203,$A13,风险登记册!$F$4:$F$203,IF($B$2="全部","<>",$B$2)) | F13: =COUNTIFS(风险登记册!$R$4:$R$203,"高",风险登记册!$C$4:$C$203,$A13,风险登记册!$F$4:$F$203,IF($B$2="全部","<>",$B$2)) | G13: =IFERROR(AVERAGEIFS(风险登记册!$V$4:$V$203,风险登记册!$C$4:$C$203,$A13,风险登记册!$F$4:$F$203,IF($B$2="全部","<>",$B$2)),"—")
A14: 人力资源 | B14: =COUNTIFS(风险登记册!$C$4:$C$203,$A14,风险登记册!$F$4:$F$203,IF($B$2="全部","<>",$B$2)) | C14: =IFERROR(ROUND(AVERAGEIFS(风险登记册!$Q$4:$Q$203,风险登记册!$C$4:$C$203,$A14,风险登记册!$F$4:$F$203,IF($B$2="全部","<>",$B$2)),2),"—") | D14: =IFERROR(MAXIFS(风险登记册!$Q$4:$Q$203,风险登记册!$C$4:$C$203,$A14,风险登记册!$F$4:$F$203,IF($B$2="全部","<>",$B$2)),"—") | E14: =COUNTIFS(风险登记册!$R$4:$R$203,"极高",风险登记册!$C$4:$C$203,$A14,风险登记册!$F$4:$F$203,IF($B$2="全部","<>",$B$2)) | F14: =COUNTIFS(风险登记册!$R$4:$R$203,"高",风险登记册!$C$4:$C$203,$A14,风险登记册!$F$4:$F$203,IF($B$2="全部","<>",$B$2)) | G14: =IFERROR(AVERAGEIFS(风险登记册!$V$4:$V$203,风险登记册!$C$4:$C$203,$A14,风险登记册!$F$4:$F$203,IF($B$2="全部","<>",$B$2)),"—")
A15: 信息系统 | B15: =COUNTIFS(风险登记册!$C$4:$C$203,$A15,风险登记册!$F$4:$F$203,IF($B$2="全部","<>",$B$2)) | C15: =IFERROR(ROUND(AVERAGEIFS(风险登记册!$Q$4:$Q$203,风险登记册!$C$4:$C$203,$A15,风险登记册!$F$4:$F$203,IF($B$2="全部","<>",$B$2)),2),"—") | D15: =IFERROR(MAXIFS(风险登记册!$Q$4:$Q$203,风险登记册!$C$4:$C$203,$A15,风险登记册!$F$4:$F$203,IF($B$2="全部","<>",$B$2)),"—") | E15: =COUNTIFS(风险登记册!$R$4:$R$203,"极高",风险登记册!$C$4:$C$203,$A15,风险登记册!$F$4:$F$203,IF($B$2="全部","<>",$B$2)) | F15: =COUNTIFS(风险登记册!$R$4:$R$203,"高",风险登记册!$C$4:$C$203,$A15,风险登记册!$F$4:$F$203,IF($B$2="全部","<>",$B$2)) | G15: =IFERROR(AVERAGEIFS(风险登记册!$V$4:$V$203,风险登记册!$C$4:$C$203,$A15,风险登记册!$F$4:$F$203,IF($B$2="全部","<>",$B$2)),"—")
A16: 合规与法律 | B16: =COUNTIFS(风险登记册!$C$4:$C$203,$A16,风险登记册!$F$4:$F$203,IF($B$2="全部","<>",$B$2)) | C16: =IFERROR(ROUND(AVERAGEIFS(风险登记册!$Q$4:$Q$203,风险登记册!$C$4:$C$203,$A16,风险登记册!$F$4:$F$203,IF($B$2="全部","<>",$B$2)),2),"—") | D16: =IFERROR(MAXIFS(风险登记册!$Q$4:$Q$203,风险登记册!$C$4:$C$203,$A16,风险登记册!$F$4:$F$203,IF($B$2="全部","<>",$B$2)),"—") | E16: =COUNTIFS(风险登记册!$R$4:$R$203,"极高",风险登记册!$C$4:$C$203,$A16,风险登记册!$F$4:$F$203,IF($B$2="全部","<>",$B$2)) | F16: =COUNTIFS(风险登记册!$R$4:$R$203,"高",风险登记册!$C$4:$C$203,$A16,风险登记册!$F$4:$F$203,IF($B$2="全部","<>",$B$2)) | G16: =IFERROR(AVERAGEIFS(风险登记册!$V$4:$V$203,风险登记册!$C$4:$C$203,$A16,风险登记册!$F$4:$F$203,IF($B$2="全部","<>",$B$2)),"—")
A17: 安全环保 | B17: =COUNTIFS(风险登记册!$C$4:$C$203,$A17,风险登记册!$F$4:$F$203,IF($B$2="全部","<>",$B$2)) | C17: =IFERROR(ROUND(AVERAGEIFS(风险登记册!$Q$4:$Q$203,风险登记册!$C$4:$C$203,$A17,风险登记册!$F$4:$F$203,IF($B$2="全部","<>",$B$2)),2),"—") | D17: =IFERROR(MAXIFS(风险登记册!$Q$4:$Q$203,风险登记册!$C$4:$C$203,$A17,风险登记册!$F$4:$F$203,IF($B$2="全部","<>",$B$2)),"—") | E17: =COUNTIFS(风险登记册!$R$4:$R$203,"极高",风险登记册!$C$4:$C$203,$A17,风险登记册!$F$4:$F$203,IF($B$2="全部","<>",$B$2)) | F17: =COUNTIFS(风险登记册!$R$4:$R$203,"高",风险登记册!$C$4:$C$203,$A17,风险登记册!$F$4:$F$203,IF($B$2="全部","<>",$B$2)) | G17: =IFERROR(AVERAGEIFS(风险登记册!$V$4:$V$203,风险登记册!$C$4:$C$203,$A17,风险登记册!$F$4:$F$203,IF($B$2="全部","<>",$B$2)),"—")
A19: 二、年度审计优先级清单（按剩余风险降序排名；可用筛选按排名/领域过滤）
A20: 排名 | B20: 风险编号 | C20: 风险名称 | D20: 所属领域 | E20: 责任部门 | F20: 可能性 | G20: 固有风险 | H20: 最弱控制分 | I20: 剩余风险 | J20: 剩余等级 | K20: 建议频次
A21: =IF($B21="","",COUNTIFS(风险登记册!$F$4:$F$203,IF($B$2="全部","<>",$B$2),风险登记册!$Q$4:$Q$203,">"&$I21)+COUNTIFS(风险登记册!$F$4:$F$203,IF($B$2="全部","<>",$B$2),风险登记册!$Q$4:$Q$203,$I21,风险登记册!$A$4:$A$203,"<"&$B21)+1) | B21: =IF($B21="","",风险登记册!A4) | C21: =IF($B21="","",风险登记册!B4) | D21: =IF($B21="","",风险登记册!C4) | E21: =IF($B21="","",风险登记册!E4) | F21: =IF($B21="","",风险登记册!G4) | G21: =IF($B21="","",风险登记册!N4) | H21: =IF($B21="","",风险登记册!O4) | I21: =IF($B21="","",风险登记册!Q4) | J21: =IF($B21="","",风险登记册!R4) | K21: =IF($B21="","",IF($J21="极高","每年必审",IF($J21="高","每年审计",IF($J21="中","两年一轮","按需抽查"))))
A22: =IF($B22="","",COUNTIFS(风险登记册!$F$4:$F$203,IF($B$2="全部","<>",$B$2),风险登记册!$Q$4:$Q$203,">"&$I22)+COUNTIFS(风险登记册!$F$4:$F$203,IF($B$2="全部","<>",$B$2),风险登记册!$Q$4:$Q$203,$I22,风险登记册!$A$4:$A$203,"<"&$B22)+1) | B22: =IF($B22="","",风险登记册!A5) | C22: =IF($B22="","",风险登记册!B5) | D22: =IF($B22="","",风险登记册!C5) | E22: =IF($B22="","",风险登记册!E5) | F22: =IF($B22="","",风险登记册!G5) | G22: =IF($B22="","",风险登记册!N5) | H22: =IF($B22="","",风险登记册!O5) | I22: =IF($B22="","",风险登记册!Q5) | J22: =IF($B22="","",风险登记册!R5) | K22: =IF($B22="","",IF($J22="极高","每年必审",IF($J22="高","每年审计",IF($J22="中","两年一轮","按需抽查"))))
A23: =IF($B23="","",COUNTIFS(风险登记册!$F$4:$F$203,IF($B$2="全部","<>",$B$2),风险登记册!$Q$4:$Q$203,">"&$I23)+COUNTIFS(风险登记册!$F$4:$F$203,IF($B$2="全部","<>",$B$2),风险登记册!$Q$4:$Q$203,$I23,风险登记册!$A$4:$A$203,"<"&$B23)+1) | B23: =IF($B23="","",风险登记册!A6) | C23: =IF($B23="","",风险登记册!B6) | D23: =IF($B23="","",风险登记册!C6) | E23: =IF($B23="","",风险登记册!E6) | F23: =IF($B23="","",风险登记册!G6) | G23: =IF($B23="","",风险登记册!N6) | H23: =IF($B23="","",风险登记册!O6) | I23: =IF($B23="","",风险登记册!Q6) | J23: =IF($B23="","",风险登记册!R6) | K23: =IF($B23="","",IF($J23="极高","每年必审",IF($J23="高","每年审计",IF($J23="中","两年一轮","按需抽查"))))
A24: =IF($B24="","",COUNTIFS(风险登记册!$F$4:$F$203,IF($B$2="全部","<>",$B$2),风险登记册!$Q$4:$Q$203,">"&$I24)+COUNTIFS(风险登记册!$F$4:$F$203,IF($B$2="全部","<>",$B$2),风险登记册!$Q$4:$Q$203,$I24,风险登记册!$A$4:$A$203,"<"&$B24)+1) | B24: =IF($B24="","",风险登记册!A7) | C24: =IF($B24="","",风险登记册!B7) | D24: =IF($B24="","",风险登记册!C7) | E24: =IF($B24="","",风险登记册!E7) | F24: =IF($B24="","",风险登记册!G7) | G24: =IF($B24="","",风险登记册!N7) | H24: =IF($B24="","",风险登记册!O7) | I24: =IF($B24="","",风险登记册!Q7) | J24: =IF($B24="","",风险登记册!R7) | K24: =IF($B24="","",IF($J24="极高","每年必审",IF($J24="高","每年审计",IF($J24="中","两年一轮","按需抽查"))))
A25: =IF($B25="","",COUNTIFS(风险登记册!$F$4:$F$203,IF($B$2="全部","<>",$B$2),风险登记册!$Q$4:$Q$203,">"&$I25)+COUNTIFS(风险登记册!$F$4:$F$203,IF($B$2="全部","<>",$B$2),风险登记册!$Q$4:$Q$203,$I25,风险登记册!$A$4:$A$203,"<"&$B25)+1) | B25: =IF($B25="","",风险登记册!A8) | C25: =IF($B25="","",风险登记册!B8) | D25: =IF($B25="","",风险登记册!C8) | E25: =IF($B25="","",风险登记册!E8) | F25: =IF($B25="","",风险登记册!G8) | G25: =IF($B25="","",风险登记册!N8) | H25: =IF($B25="","",风险登记册!O8) | I25: =IF($B25="","",风险登记册!Q8) | J25: =IF($B25="","",风险登记册!R8) | K25: =IF($B25="","",IF($J25="极高","每年必审",IF($J25="高","每年审计",IF($J25="中","两年一轮","按需抽查"))))
A26: =IF($B26="","",COUNTIFS(风险登记册!$F$4:$F$203,IF($B$2="全部","<>",$B$2),风险登记册!$Q$4:$Q$203,">"&$I26)+COUNTIFS(风险登记册!$F$4:$F$203,IF($B$2="全部","<>",$B$2),风险登记册!$Q$4:$Q$203,$I26,风险登记册!$A$4:$A$203,"<"&$B26)+1) | B26: =IF($B26="","",风险登记册!A9) | C26: =IF($B26="","",风险登记册!B9) | D26: =IF($B26="","",风险登记册!C9) | E26: =IF($B26="","",风险登记册!E9) | F26: =IF($B26="","",风险登记册!G9) | G26: =IF($B26="","",风险登记册!N9) | H26: =IF($B26="","",风险登记册!O9) | I26: =IF($B26="","",风险登记册!Q9) | J26: =IF($B26="","",风险登记册!R9) | K26: =IF($B26="","",IF($J26="极高","每年必审",IF($J26="高","每年审计",IF($J26="中","两年一轮","按需抽查"))))
A27: =IF($B27="","",COUNTIFS(风险登记册!$F$4:$F$203,IF($B$2="全部","<>",$B$2),风险登记册!$Q$4:$Q$203,">"&$I27)+COUNTIFS(风险登记册!$F$4:$F$203,IF($B$2="全部","<>",$B$2),风险登记册!$Q$4:$Q$203,$I27,风险登记册!$A$4:$A$203,"<"&$B27)+1) | B27: =IF($B27="","",风险登记册!A10) | C27: =IF($B27="","",风险登记册!B10) | D27: =IF($B27="","",风险登记册!C10) | E27: =IF($B27="","",风险登记册!E10) | F27: =IF($B27="","",风险登记册!G10) | G27: =IF($B27="","",风险登记册!N10) | H27: =IF($B27="","",风险登记册!O10) | I27: =IF($B27="","",风险登记册!Q10) | J27: =IF($B27="","",风险登记册!R10) | K27: =IF($B27="","",IF($J27="极高","每年必审",IF($J27="高","每年审计",IF($J27="中","两年一轮","按需抽查"))))
A28: =IF($B28="","",COUNTIFS(风险登记册!$F$4:$F$203,IF($B$2="全部","<>",$B$2),风险登记册!$Q$4:$Q$203,">"&$I28)+COUNTIFS(风险登记册!$F$4:$F$203,IF($B$2="全部","<>",$B$2),风险登记册!$Q$4:$Q$203,$I28,风险登记册!$A$4:$A$203,"<"&$B28)+1) | B28: =IF($B28="","",风险登记册!A11) | C28: =IF($B28="","",风险登记册!B11) | D28: =IF($B28="","",风险登记册!C11) | E28: =IF($B28="","",风险登记册!E11) | F28: =IF($B28="","",风险登记册!G11) | G28: =IF($B28="","",风险登记册!N11) | H28: =IF($B28="","",风险登记册!O11) | I28: =IF($B28="","",风险登记册!Q11) | J28: =IF($B28="","",风险登记册!R11) | K28: =IF($B28="","",IF($J28="极高","每年必审",IF($J28="高","每年审计",IF($J28="中","两年一轮","按需抽查"))))
A29: =IF($B29="","",COUNTIFS(风险登记册!$F$4:$F$203,IF($B$2="全部","<>",$B$2),风险登记册!$Q$4:$Q$203,">"&$I29)+COUNTIFS(风险登记册!$F$4:$F$203,IF($B$2="全部","<>",$B$2),风险登记册!$Q$4:$Q$203,$I29,风险登记册!$A$4:$A$203,"<"&$B29)+1) | B29: =IF($B29="","",风险登记册!A12) | C29: =IF($B29="","",风险登记册!B12) | D29: =IF($B29="","",风险登记册!C12) | E29: =IF($B29="","",风险登记册!E12) | F29: =IF($B29="","",风险登记册!G12) | G29: =IF($B29="","",风险登记册!N12) | H29: =IF($B29="","",风险登记册!O12) | I29: =IF($B29="","",风险登记册!Q12) | J29: =IF($B29="","",风险登记册!R12) | K29: =IF($B29="","",IF($J29="极高","每年必审",IF($J29="高","每年审计",IF($J29="中","两年一轮","按需抽查"))))
A30: =IF($B30="","",COUNTIFS(风险登记册!$F$4:$F$203,IF($B$2="全部","<>",$B$2),风险登记册!$Q$4:$Q$203,">"&$I30)+COUNTIFS(风险登记册!$F$4:$F$203,IF($B$2="全部","<>",$B$2),风险登记册!$Q$4:$Q$203,$I30,风险登记册!$A$4:$A$203,"<"&$B30)+1) | B30: =IF($B30="","",风险登记册!A13) | C30: =IF($B30="","",风险登记册!B13) | D30: =IF($B30="","",风险登记册!C13) | E30: =IF($B30="","",风险登记册!E13) | F30: =IF($B30="","",风险登记册!G13) | G30: =IF($B30="","",风险登记册!N13) | H30: =IF($B30="","",风险登记册!O13) | I30: =IF($B30="","",风险登记册!Q13) | J30: =IF($B30="","",风险登记册!R13) | K30: =IF($B30="","",IF($J30="极高","每年必审",IF($J30="高","每年审计",IF($J30="中","两年一轮","按需抽查"))))
A31: =IF($B31="","",COUNTIFS(风险登记册!$F$4:$F$203,IF($B$2="全部","<>",$B$2),风险登记册!$Q$4:$Q$203,">"&$I31)+COUNTIFS(风险登记册!$F$4:$F$203,IF($B$2="全部","<>",$B$2),风险登记册!$Q$4:$Q$203,$I31,风险登记册!$A$4:$A$203,"<"&$B31)+1) | B31: =IF($B31="","",风险登记册!A14) | C31: =IF($B31="","",风险登记册!B14) | D31: =IF($B31="","",风险登记册!C14) | E31: =IF($B31="","",风险登记册!E14) | F31: =IF($B31="","",风险登记册!G14) | G31: =IF($B31="","",风险登记册!N14) | H31: =IF($B31="","",风险登记册!O14) | I31: =IF($B31="","",风险登记册!Q14) | J31: =IF($B31="","",风险登记册!R14) | K31: =IF($B31="","",IF($J31="极高","每年必审",IF($J31="高","每年审计",IF($J31="中","两年一轮","按需抽查"))))
A32: =IF($B32="","",COUNTIFS(风险登记册!$F$4:$F$203,IF($B$2="全部","<>",$B$2),风险登记册!$Q$4:$Q$203,">"&$I32)+COUNTIFS(风险登记册!$F$4:$F$203,IF($B$2="全部","<>",$B$2),风险登记册!$Q$4:$Q$203,$I32,风险登记册!$A$4:$A$203,"<"&$B32)+1) | B32: =IF($B32="","",风险登记册!A15) | C32: =IF($B32="","",风险登记册!B15) | D32: =IF($B32="","",风险登记册!C15) | E32: =IF($B32="","",风险登记册!E15) | F32: =IF($B32="","",风险登记册!G15) | G32: =IF($B32="","",风险登记册!N15) | H32: =IF($B32="","",风险登记册!O15) | I32: =IF($B32="","",风险登记册!Q15) | J32: =IF($B32="","",风险登记册!R15) | K32: =IF($B32="","",IF($J32="极高","每年必审",IF($J32="高","每年审计",IF($J32="中","两年一轮","按需抽查"))))
... A100: =IF($B100="","",COUNTIFS(风险登记册!$F$4:$F$203,IF($B$2="全部","<>",$B$2),风险登记册!$Q$4:$Q$203,">"&$I100)+COUNTIFS(风险登记册!$F$4:$F$203,IF($B$2="全部","<>",$B$2),风险登记册!$Q$4:$Q$203,$I100,风险登记册!$A$4:$A$203,"<"&$B100)+1) | B100: =IF($B100="","",风险登记册!A83) | C100: =IF($B100="","",风险登记册!B83) | D100: =IF($B100="","",风险登记册!C83) | E100: =IF($B100="","",风险登记册!E83) | F100: =IF($B100="","",风险登记册!G83) | G100: =IF($B100="","",风险登记册!N83) | H100: =IF($B100="","",风险登记册!O83) | I100: =IF($B100="","",风险登记册!Q83) | J100: =IF($B100="","",风险登记册!R83) | K100: =IF($B100="","",IF($J100="极高","每年必审",IF($J100="高","每年审计",IF($J100="中","两年一轮","按需抽查"))))
